{
  "lastUpdated": "2025-08-16T09:44:47.823Z",
  "marketSentiment": 18.136439267886857,
  "ethChange": -3.835,
  "topGainers": [
    {
      "symbol": "ALPINEUSDT",
      "lastPrice": "2.10000000",
      "priceChangePercent": "39.073"
    },
    {
      "symbol": "PORTOUSDT",
      "lastPrice": "1.26300000",
      "priceChangePercent": "23.824"
    },
    {
      "symbol": "CTSIUSDT",
      "lastPrice": "0.07880000",
      "priceChangePercent": "17.437"
    },
    {
      "symbol": "EPICUSDT",
      "lastPrice": "2.29900000",
      "priceChangePercent": "17.356"
    },
    {
      "symbol": "LAZIOUSDT",
      "lastPrice": "1.15600000",
      "priceChangePercent": "12.016"
    },
    {
      "symbol": "BATUSDT",
      "lastPrice": "0.16500000",
      "priceChangePercent": "10.147"
    },
    {
      "symbol": "LAUSDT",
      "lastPrice": "0.37840000",
      "priceChangePercent": "8.798"
    },
    {
      "symbol": "LOKAUSDT",
      "lastPrice": "0.12370000",
      "priceChangePercent": "8.509"
    },
    {
      "symbol": "LUNCUSDT",
      "lastPrice": "0.00006307",
      "priceChangePercent": "7.702"
    },
    {
      "symbol": "THEUSDT",
      "lastPrice": "0.46570000",
      "priceChangePercent": "7.131"
    },
    {
      "symbol": "KAVAUSDT",
      "lastPrice": "0.38270000",
      "priceChangePercent": "6.217"
    },
    {
      "symbol": "ACAUSDT",
      "lastPrice": "0.03040000",
      "priceChangePercent": "5.556"
    },
    {
      "symbol": "TSTUSDT",
      "lastPrice": "0.02718000",
      "priceChangePercent": "5.553"
    },
    {
      "symbol": "ILVUSDT",
      "lastPrice": "17.22000000",
      "priceChangePercent": "5.321"
    },
    {
      "symbol": "SNXUSDT",
      "lastPrice": "0.70300000",
      "priceChangePercent": "5.082"
    },
    {
      "symbol": "AEURUSDT",
      "lastPrice": "1.11020000",
      "priceChangePercent": "4.686"
    },
    {
      "symbol": "LUNAUSDT",
      "lastPrice": "0.16120000",
      "priceChangePercent": "4.404"
    },
    {
      "symbol": "ERAUSDT",
      "lastPrice": "0.96990000",
      "priceChangePercent": "3.977"
    },
    {
      "symbol": "BERAUSDT",
      "lastPrice": "2.22900000",
      "priceChangePercent": "3.723"
    },
    {
      "symbol": "FORTHUSDT",
      "lastPrice": "2.95800000",
      "priceChangePercent": "3.644"
    }
  ],
  "allTickers": [
    {
      "symbol": "ALPINEUSDT",
      "lastPrice": "2.10000000"
    },
    {
      "symbol": "PORTOUSDT",
      "lastPrice": "1.26300000"
    },
    {
      "symbol": "CTSIUSDT",
      "lastPrice": "0.07880000"
    },
    {
      "symbol": "EPICUSDT",
      "lastPrice": "2.29900000"
    },
    {
      "symbol": "LAZIOUSDT",
      "lastPrice": "1.15600000"
    },
    {
      "symbol": "BATUSDT",
      "lastPrice": "0.16500000"
    },
    {
      "symbol": "LAUSDT",
      "lastPrice": "0.37840000"
    },
    {
      "symbol": "LOKAUSDT",
      "lastPrice": "0.12370000"
    },
    {
      "symbol": "LUNCUSDT",
      "lastPrice": "0.00006307"
    },
    {
      "symbol": "THEUSDT",
      "lastPrice": "0.46570000"
    },
    {
      "symbol": "KAVAUSDT",
      "lastPrice": "0.38270000"
    },
    {
      "symbol": "ACAUSDT",
      "lastPrice": "0.03040000"
    },
    {
      "symbol": "TSTUSDT",
      "lastPrice": "0.02718000"
    },
    {
      "symbol": "ILVUSDT",
      "lastPrice": "17.22000000"
    },
    {
      "symbol": "SNXUSDT",
      "lastPrice": "0.70300000"
    },
    {
      "symbol": "AEURUSDT",
      "lastPrice": "1.11020000"
    },
    {
      "symbol": "LUNAUSDT",
      "lastPrice": "0.16120000"
    },
    {
      "symbol": "ERAUSDT",
      "lastPrice": "0.96990000"
    },
    {
      "symbol": "BERAUSDT",
      "lastPrice": "2.22900000"
    },
    {
      "symbol": "FORTHUSDT",
      "lastPrice": "2.95800000"
    },
    {
      "symbol": "USTCUSDT",
      "lastPrice": "0.01377000"
    },
    {
      "symbol": "XTZUSDT",
      "lastPrice": "0.87230000"
    },
    {
      "symbol": "GASUSDT",
      "lastPrice": "3.43200000"
    },
    {
      "symbol": "GLMUSDT",
      "lastPrice": "0.26070000"
    },
    {
      "symbol": "MLNUSDT",
      "lastPrice": "9.13000000"
    },
    {
      "symbol": "HUMAUSDT",
      "lastPrice": "0.03561000"
    },
    {
      "symbol": "1000CHEEMSUSDT",
      "lastPrice": "0.00132900"
    },
    {
      "symbol": "NOTUSDT",
      "lastPrice": "0.00196700"
    },
    {
      "symbol": "TNSRUSDT",
      "lastPrice": "0.13090000"
    },
    {
      "symbol": "STEEMUSDT",
      "lastPrice": "0.13550000"
    },
    {
      "symbol": "PYRUSDT",
      "lastPrice": "1.12800000"
    },
    {
      "symbol": "PROVEUSDT",
      "lastPrice": "1.30990000"
    },
    {
      "symbol": "FISUSDT",
      "lastPrice": "0.12810000"
    },
    {
      "symbol": "OMNIUSDT",
      "lastPrice": "4.09000000"
    },
    {
      "symbol": "LRCUSDT",
      "lastPrice": "0.08780000"
    },
    {
      "symbol": "FORMUSDT",
      "lastPrice": "3.80390000"
    },
    {
      "symbol": "DEXEUSDT",
      "lastPrice": "7.32300000"
    },
    {
      "symbol": "DEGOUSDT",
      "lastPrice": "1.27500000"
    },
    {
      "symbol": "XRPUSDT",
      "lastPrice": "3.15250000"
    },
    {
      "symbol": "GLMRUSDT",
      "lastPrice": "0.07540000"
    },
    {
      "symbol": "DOGEUSDT",
      "lastPrice": "0.23404000"
    },
    {
      "symbol": "RADUSDT",
      "lastPrice": "0.64200000"
    },
    {
      "symbol": "WINUSDT",
      "lastPrice": "0.00006175"
    },
    {
      "symbol": "TONUSDT",
      "lastPrice": "3.48600000"
    },
    {
      "symbol": "SANDUSDT",
      "lastPrice": "0.29060000"
    },
    {
      "symbol": "UMAUSDT",
      "lastPrice": "1.28600000"
    },
    {
      "symbol": "AUDIOUSDT",
      "lastPrice": "0.06290000"
    },
    {
      "symbol": "XLMUSDT",
      "lastPrice": "0.43210000"
    },
    {
      "symbol": "API3USDT",
      "lastPrice": "0.73500000"
    },
    {
      "symbol": "DFUSDT",
      "lastPrice": "0.02895000"
    },
    {
      "symbol": "VANAUSDT",
      "lastPrice": "4.29700000"
    },
    {
      "symbol": "STOUSDT",
      "lastPrice": "0.09360000"
    },
    {
      "symbol": "HOTUSDT",
      "lastPrice": "0.00095100"
    },
    {
      "symbol": "GALAUSDT",
      "lastPrice": "0.01706000"
    },
    {
      "symbol": "OGNUSDT",
      "lastPrice": "0.06110000"
    },
    {
      "symbol": "ORDIUSDT",
      "lastPrice": "9.16500000"
    },
    {
      "symbol": "ZRXUSDT",
      "lastPrice": "0.24920000"
    },
    {
      "symbol": "CATIUSDT",
      "lastPrice": "0.08860000"
    },
    {
      "symbol": "IOTAUSDT",
      "lastPrice": "0.20320000"
    },
    {
      "symbol": "GUNUSDT",
      "lastPrice": "0.02772000"
    },
    {
      "symbol": "NEWTUSDT",
      "lastPrice": "0.32680000"
    },
    {
      "symbol": "RAREUSDT",
      "lastPrice": "0.05520000"
    },
    {
      "symbol": "STRKUSDT",
      "lastPrice": "0.13400000"
    },
    {
      "symbol": "AXSUSDT",
      "lastPrice": "2.39800000"
    },
    {
      "symbol": "CELRUSDT",
      "lastPrice": "0.00805000"
    },
    {
      "symbol": "ATAUSDT",
      "lastPrice": "0.04850000"
    },
    {
      "symbol": "ADAUSDT",
      "lastPrice": "0.94960000"
    },
    {
      "symbol": "DOGSUSDT",
      "lastPrice": "0.00013630"
    },
    {
      "symbol": "LDOUSDT",
      "lastPrice": "1.39100000"
    },
    {
      "symbol": "DASHUSDT",
      "lastPrice": "22.59000000"
    },
    {
      "symbol": "ARPAUSDT",
      "lastPrice": "0.02252000"
    },
    {
      "symbol": "TRUMPUSDT",
      "lastPrice": "9.22000000"
    },
    {
      "symbol": "OXTUSDT",
      "lastPrice": "0.05530000"
    },
    {
      "symbol": "SXTUSDT",
      "lastPrice": "0.08390000"
    },
    {
      "symbol": "MBLUSDT",
      "lastPrice": "0.00227100"
    },
    {
      "symbol": "CFXUSDT",
      "lastPrice": "0.17940000"
    },
    {
      "symbol": "HIFIUSDT",
      "lastPrice": "0.09220000"
    },
    {
      "symbol": "GRTUSDT",
      "lastPrice": "0.09380000"
    },
    {
      "symbol": "REDUSDT",
      "lastPrice": "0.37940000"
    },
    {
      "symbol": "LUMIAUSDT",
      "lastPrice": "0.32000000"
    },
    {
      "symbol": "SHIBUSDT",
      "lastPrice": "0.00001302"
    },
    {
      "symbol": "HYPERUSDT",
      "lastPrice": "0.35790000"
    },
    {
      "symbol": "ACTUSDT",
      "lastPrice": "0.04040000"
    },
    {
      "symbol": "XECUSDT",
      "lastPrice": "0.00002090"
    },
    {
      "symbol": "THETAUSDT",
      "lastPrice": "0.84200000"
    },
    {
      "symbol": "ACHUSDT",
      "lastPrice": "0.02157000"
    },
    {
      "symbol": "SYNUSDT",
      "lastPrice": "0.13690000"
    },
    {
      "symbol": "RVNUSDT",
      "lastPrice": "0.01384000"
    },
    {
      "symbol": "COOKIEUSDT",
      "lastPrice": "0.14310000"
    },
    {
      "symbol": "REQUSDT",
      "lastPrice": "0.15130000"
    },
    {
      "symbol": "SCUSDT",
      "lastPrice": "0.00312800"
    },
    {
      "symbol": "RIFUSDT",
      "lastPrice": "0.05520000"
    },
    {
      "symbol": "CTKUSDT",
      "lastPrice": "0.34760000"
    },
    {
      "symbol": "BARUSDT",
      "lastPrice": "1.32600000"
    },
    {
      "symbol": "BANDUSDT",
      "lastPrice": "0.67000000"
    },
    {
      "symbol": "QTUMUSDT",
      "lastPrice": "2.12400000"
    },
    {
      "symbol": "ALTUSDT",
      "lastPrice": "0.03558000"
    },
    {
      "symbol": "MANAUSDT",
      "lastPrice": "0.29430000"
    },
    {
      "symbol": "FUNUSDT",
      "lastPrice": "0.00948900"
    },
    {
      "symbol": "CHZUSDT",
      "lastPrice": "0.04071000"
    },
    {
      "symbol": "EURIUSDT",
      "lastPrice": "1.16810000"
    },
    {
      "symbol": "VTHOUSDT",
      "lastPrice": "0.00191200"
    },
    {
      "symbol": "RENDERUSDT",
      "lastPrice": "3.90600000"
    },
    {
      "symbol": "GNSUSDT",
      "lastPrice": "2.05500000"
    },
    {
      "symbol": "EURUSDT",
      "lastPrice": "1.16820000"
    },
    {
      "symbol": "TUSDUSDT",
      "lastPrice": "0.99760000"
    },
    {
      "symbol": "FLOKIUSDT",
      "lastPrice": "0.00010608"
    },
    {
      "symbol": "APEUSDT",
      "lastPrice": "0.60940000"
    },
    {
      "symbol": "XUSDUSDT",
      "lastPrice": "0.99950000"
    },
    {
      "symbol": "BCCUSDT",
      "lastPrice": "0.00000000"
    },
    {
      "symbol": "NEOUSDT",
      "lastPrice": "6.27000000"
    },
    {
      "symbol": "EOSUSDT",
      "lastPrice": "0.00000000"
    },
    {
      "symbol": "VENUSDT",
      "lastPrice": "0.00000000"
    },
    {
      "symbol": "NULSUSDT",
      "lastPrice": "0.00000000"
    },
    {
      "symbol": "PAXUSDT",
      "lastPrice": "0.00000000"
    },
    {
      "symbol": "BCHABCUSDT",
      "lastPrice": "0.00000000"
    },
    {
      "symbol": "BCHSVUSDT",
      "lastPrice": "0.00000000"
    },
    {
      "symbol": "WAVESUSDT",
      "lastPrice": "0.00000000"
    },
    {
      "symbol": "BTTUSDT",
      "lastPrice": "0.00000000"
    },
    {
      "symbol": "USDSUSDT",
      "lastPrice": "0.00000000"
    },
    {
      "symbol": "XMRUSDT",
      "lastPrice": "0.00000000"
    },
    {
      "symbol": "NANOUSDT",
      "lastPrice": "0.00000000"
    },
    {
      "symbol": "OMGUSDT",
      "lastPrice": "0.00000000"
    },
    {
      "symbol": "MITHUSDT",
      "lastPrice": "0.00000000"
    },
    {
      "symbol": "MATICUSDT",
      "lastPrice": "0.00000000"
    },
    {
      "symbol": "FTMUSDT",
      "lastPrice": "0.00000000"
    },
    {
      "symbol": "USDSBUSDT",
      "lastPrice": "0.00000000"
    },
    {
      "symbol": "GTOUSDT",
      "lastPrice": "0.00000000"
    },
    {
      "symbol": "ERDUSDT",
      "lastPrice": "0.00000000"
    },
    {
      "symbol": "NPXSUSDT",
      "lastPrice": "0.00000000"
    },
    {
      "symbol": "COCOSUSDT",
      "lastPrice": "0.00000000"
    },
    {
      "symbol": "TOMOUSDT",
      "lastPrice": "0.00000000"
    },
    {
      "symbol": "PERLUSDT",
      "lastPrice": "0.00000000"
    },
    {
      "symbol": "MFTUSDT",
      "lastPrice": "0.00000000"
    },
    {
      "symbol": "KEYUSDT",
      "lastPrice": "0.00000000"
    },
    {
      "symbol": "STORMUSDT",
      "lastPrice": "0.00000000"
    },
    {
      "symbol": "DOCKUSDT",
      "lastPrice": "0.00000000"
    },
    {
      "symbol": "BUSDUSDT",
      "lastPrice": "0.00000000"
    },
    {
      "symbol": "BEAMUSDT",
      "lastPrice": "0.00000000"
    },
    {
      "symbol": "RENUSDT",
      "lastPrice": "0.00000000"
    },
    {
      "symbol": "HCUSDT",
      "lastPrice": "0.00000000"
    },
    {
      "symbol": "MCOUSDT",
      "lastPrice": "0.00000000"
    },
    {
      "symbol": "CTXCUSDT",
      "lastPrice": "0.00000000"
    },
    {
      "symbol": "TROYUSDT",
      "lastPrice": "0.00000000"
    },
    {
      "symbol": "VITEUSDT",
      "lastPrice": "0.00000000"
    },
    {
      "symbol": "DREPUSDT",
      "lastPrice": "0.00000000"
    },
    {
      "symbol": "BULLUSDT",
      "lastPrice": "0.00000000"
    },
    {
      "symbol": "BEARUSDT",
      "lastPrice": "0.00000000"
    },
    {
      "symbol": "ETHBULLUSDT",
      "lastPrice": "0.00000000"
    },
    {
      "symbol": "ETHBEARUSDT",
      "lastPrice": "0.00000000"
    },
    {
      "symbol": "TCTUSDT",
      "lastPrice": "0.00000000"
    },
    {
      "symbol": "WRXUSDT",
      "lastPrice": "0.00000000"
    },
    {
      "symbol": "BTSUSDT",
      "lastPrice": "0.00000000"
    },
    {
      "symbol": "EOSBULLUSDT",
      "lastPrice": "0.00000000"
    },
    {
      "symbol": "EOSBEARUSDT",
      "lastPrice": "0.00000000"
    },
    {
      "symbol": "XRPBULLUSDT",
      "lastPrice": "0.00000000"
    },
    {
      "symbol": "XRPBEARUSDT",
      "lastPrice": "0.00000000"
    },
    {
      "symbol": "STRATUSDT",
      "lastPrice": "0.00000000"
    },
    {
      "symbol": "AIONUSDT",
      "lastPrice": "0.00000000"
    },
    {
      "symbol": "BNBBULLUSDT",
      "lastPrice": "0.00000000"
    },
    {
      "symbol": "BNBBEARUSDT",
      "lastPrice": "0.00000000"
    },
    {
      "symbol": "STPTUSDT",
      "lastPrice": "0.00000000"
    },
    {
      "symbol": "WTCUSDT",
      "lastPrice": "0.00000000"
    },
    {
      "symbol": "XZCUSDT",
      "lastPrice": "0.00000000"
    },
    {
      "symbol": "BTCUPUSDT",
      "lastPrice": "0.00000000"
    },
    {
      "symbol": "BTCDOWNUSDT",
      "lastPrice": "0.00000000"
    },
    {
      "symbol": "GXSUSDT",
      "lastPrice": "0.00000000"
    },
    {
      "symbol": "LENDUSDT",
      "lastPrice": "0.00000000"
    },
    {
      "symbol": "STMXUSDT",
      "lastPrice": "0.00000000"
    },
    {
      "symbol": "REPUSDT",
      "lastPrice": "0.00000000"
    },
    {
      "symbol": "PNTUSDT",
      "lastPrice": "0.00000000"
    },
    {
      "symbol": "BKRWUSDT",
      "lastPrice": "0.00000000"
    },
    {
      "symbol": "ETHUPUSDT",
      "lastPrice": "0.00000000"
    },
    {
      "symbol": "ETHDOWNUSDT",
      "lastPrice": "0.00000000"
    },
    {
      "symbol": "ADAUPUSDT",
      "lastPrice": "0.00000000"
    },
    {
      "symbol": "ADADOWNUSDT",
      "lastPrice": "0.00000000"
    },
    {
      "symbol": "LINKUPUSDT",
      "lastPrice": "0.00000000"
    },
    {
      "symbol": "LINKDOWNUSDT",
      "lastPrice": "0.00000000"
    },
    {
      "symbol": "GBPUSDT",
      "lastPrice": "0.00000000"
    },
    {
      "symbol": "DAIUSDT",
      "lastPrice": "0.00000000"
    },
    {
      "symbol": "BNBUPUSDT",
      "lastPrice": "0.00000000"
    },
    {
      "symbol": "BNBDOWNUSDT",
      "lastPrice": "0.00000000"
    },
    {
      "symbol": "XTZUPUSDT",
      "lastPrice": "0.00000000"
    },
    {
      "symbol": "XTZDOWNUSDT",
      "lastPrice": "0.00000000"
    },
    {
      "symbol": "AUDUSDT",
      "lastPrice": "0.00000000"
    },
    {
      "symbol": "BALUSDT",
      "lastPrice": "0.00000000"
    },
    {
      "symbol": "BLZUSDT",
      "lastPrice": "0.00000000"
    },
    {
      "symbol": "IRISUSDT",
      "lastPrice": "0.00000000"
    },
    {
      "symbol": "SRMUSDT",
      "lastPrice": "0.00000000"
    },
    {
      "symbol": "ANTUSDT",
      "lastPrice": "0.00000000"
    },
    {
      "symbol": "OCEANUSDT",
      "lastPrice": "0.00000000"
    },
    {
      "symbol": "WNXMUSDT",
      "lastPrice": "0.00000000"
    },
    {
      "symbol": "BZRXUSDT",
      "lastPrice": "0.00000000"
    },
    {
      "symbol": "YFIIUSDT",
      "lastPrice": "0.00000000"
    },
    {
      "symbol": "EOSUPUSDT",
      "lastPrice": "0.00000000"
    },
    {
      "symbol": "EOSDOWNUSDT",
      "lastPrice": "0.00000000"
    },
    {
      "symbol": "TRXUPUSDT",
      "lastPrice": "0.00000000"
    },
    {
      "symbol": "TRXDOWNUSDT",
      "lastPrice": "0.00000000"
    },
    {
      "symbol": "XRPUPUSDT",
      "lastPrice": "0.00000000"
    },
    {
      "symbol": "XRPDOWNUSDT",
      "lastPrice": "0.00000000"
    },
    {
      "symbol": "DOTUPUSDT",
      "lastPrice": "0.00000000"
    },
    {
      "symbol": "DOTDOWNUSDT",
      "lastPrice": "0.00000000"
    },
    {
      "symbol": "WINGUSDT",
      "lastPrice": "0.00000000"
    },
    {
      "symbol": "LTCUPUSDT",
      "lastPrice": "0.00000000"
    },
    {
      "symbol": "LTCDOWNUSDT",
      "lastPrice": "0.00000000"
    },
    {
      "symbol": "NBSUSDT",
      "lastPrice": "0.00000000"
    },
    {
      "symbol": "HNTUSDT",
      "lastPrice": "0.00000000"
    },
    {
      "symbol": "UNIUPUSDT",
      "lastPrice": "0.00000000"
    },
    {
      "symbol": "UNIDOWNUSDT",
      "lastPrice": "0.00000000"
    },
    {
      "symbol": "ORNUSDT",
      "lastPrice": "0.00000000"
    },
    {
      "symbol": "SXPUPUSDT",
      "lastPrice": "0.00000000"
    },
    {
      "symbol": "SXPDOWNUSDT",
      "lastPrice": "0.00000000"
    },
    {
      "symbol": "FILUPUSDT",
      "lastPrice": "0.00000000"
    },
    {
      "symbol": "FILDOWNUSDT",
      "lastPrice": "0.00000000"
    },
    {
      "symbol": "YFIUPUSDT",
      "lastPrice": "0.00000000"
    },
    {
      "symbol": "YFIDOWNUSDT",
      "lastPrice": "0.00000000"
    },
    {
      "symbol": "BCHUPUSDT",
      "lastPrice": "0.00000000"
    },
    {
      "symbol": "BCHDOWNUSDT",
      "lastPrice": "0.00000000"
    },
    {
      "symbol": "AKROUSDT",
      "lastPrice": "0.00000000"
    },
    {
      "symbol": "HARDUSDT",
      "lastPrice": "0.00000000"
    },
    {
      "symbol": "DNTUSDT",
      "lastPrice": "0.00000000"
    },
    {
      "symbol": "UNFIUSDT",
      "lastPrice": "0.00000000"
    },
    {
      "symbol": "XEMUSDT",
      "lastPrice": "0.00000000"
    },
    {
      "symbol": "AAVEUPUSDT",
      "lastPrice": "0.00000000"
    },
    {
      "symbol": "AAVEDOWNUSDT",
      "lastPrice": "0.00000000"
    },
    {
      "symbol": "SUSDUSDT",
      "lastPrice": "0.00000000"
    },
    {
      "symbol": "SUSHIUPUSDT",
      "lastPrice": "0.00000000"
    },
    {
      "symbol": "SUSHIDOWNUSDT",
      "lastPrice": "0.00000000"
    },
    {
      "symbol": "XLMUPUSDT",
      "lastPrice": "0.00000000"
    },
    {
      "symbol": "XLMDOWNUSDT",
      "lastPrice": "0.00000000"
    },
    {
      "symbol": "REEFUSDT",
      "lastPrice": "0.00000000"
    },
    {
      "symbol": "BTCSTUSDT",
      "lastPrice": "0.00000000"
    },
    {
      "symbol": "FIROUSDT",
      "lastPrice": "0.00000000"
    },
    {
      "symbol": "LITUSDT",
      "lastPrice": "0.00000000"
    },
    {
      "symbol": "BADGERUSDT",
      "lastPrice": "0.00000000"
    },
    {
      "symbol": "LINAUSDT",
      "lastPrice": "0.00000000"
    },
    {
      "symbol": "RAMPUSDT",
      "lastPrice": "0.00000000"
    },
    {
      "symbol": "EPSUSDT",
      "lastPrice": "0.00000000"
    },
    {
      "symbol": "AUTOUSDT",
      "lastPrice": "0.00000000"
    },
    {
      "symbol": "1INCHUPUSDT",
      "lastPrice": "0.00000000"
    },
    {
      "symbol": "1INCHDOWNUSDT",
      "lastPrice": "0.00000000"
    },
    {
      "symbol": "BTGUSDT",
      "lastPrice": "0.00000000"
    },
    {
      "symbol": "MIRUSDT",
      "lastPrice": "0.00000000"
    },
    {
      "symbol": "BURGERUSDT",
      "lastPrice": "0.00000000"
    },
    {
      "symbol": "POLSUSDT",
      "lastPrice": "0.00000000"
    },
    {
      "symbol": "MDXUSDT",
      "lastPrice": "0.00000000"
    },
    {
      "symbol": "NUUSDT",
      "lastPrice": "0.00000000"
    },
    {
      "symbol": "TORNUSDT",
      "lastPrice": "0.00000000"
    },
    {
      "symbol": "KEEPUSDT",
      "lastPrice": "0.00000000"
    },
    {
      "symbol": "ERNUSDT",
      "lastPrice": "0.00000000"
    },
    {
      "symbol": "KLAYUSDT",
      "lastPrice": "0.00000000"
    },
    {
      "symbol": "BONDUSDT",
      "lastPrice": "0.00000000"
    },
    {
      "symbol": "CLVUSDT",
      "lastPrice": "0.00000000"
    },
    {
      "symbol": "TVKUSDT",
      "lastPrice": "0.00000000"
    },
    {
      "symbol": "ALPACAUSDT",
      "lastPrice": "0.00000000"
    },
    {
      "symbol": "FORUSDT",
      "lastPrice": "0.00000000"
    },
    {
      "symbol": "TRIBEUSDT",
      "lastPrice": "0.00000000"
    },
    {
      "symbol": "ELFUSDT",
      "lastPrice": "0.00000000"
    },
    {
      "symbol": "POLYUSDT",
      "lastPrice": "0.00000000"
    },
    {
      "symbol": "VIDTUSDT",
      "lastPrice": "0.00000000"
    },
    {
      "symbol": "FRONTUSDT",
      "lastPrice": "0.00000000"
    },
    {
      "symbol": "CVPUSDT",
      "lastPrice": "0.00000000"
    },
    {
      "symbol": "BETAUSDT",
      "lastPrice": "0.00000000"
    },
    {
      "symbol": "DARUSDT",
      "lastPrice": "0.00000000"
    },
    {
      "symbol": "BNXUSDT",
      "lastPrice": "0.00000000"
    },
    {
      "symbol": "RGTUSDT",
      "lastPrice": "0.00000000"
    },
    {
      "symbol": "KP3RUSDT",
      "lastPrice": "0.00000000"
    },
    {
      "symbol": "VGXUSDT",
      "lastPrice": "0.00000000"
    },
    {
      "symbol": "PLAUSDT",
      "lastPrice": "0.00000000"
    },
    {
      "symbol": "RNDRUSDT",
      "lastPrice": "0.00000000"
    },
    {
      "symbol": "MCUSDT",
      "lastPrice": "0.00000000"
    },
    {
      "symbol": "ANYUSDT",
      "lastPrice": "0.00000000"
    },
    {
      "symbol": "OOKIUSDT",
      "lastPrice": "0.00000000"
    },
    {
      "symbol": "USTUSDT",
      "lastPrice": "0.00000000"
    },
    {
      "symbol": "ANCUSDT",
      "lastPrice": "0.00000000"
    },
    {
      "symbol": "NBTUSDT",
      "lastPrice": "0.00000000"
    },
    {
      "symbol": "MULTIUSDT",
      "lastPrice": "0.00000000"
    },
    {
      "symbol": "MOBUSDT",
      "lastPrice": "0.00000000"
    },
    {
      "symbol": "GALUSDT",
      "lastPrice": "0.00000000"
    },
    {
      "symbol": "EPXUSDT",
      "lastPrice": "0.00000000"
    },
    {
      "symbol": "NEBLUSDT",
      "lastPrice": "0.00000000"
    },
    {
      "symbol": "PROSUSDT",
      "lastPrice": "0.00000000"
    },
    {
      "symbol": "AGIXUSDT",
      "lastPrice": "0.00000000"
    },
    {
      "symbol": "VIBUSDT",
      "lastPrice": "0.00000000"
    },
    {
      "symbol": "AMBUSDT",
      "lastPrice": "0.00000000"
    },
    {
      "symbol": "BETHUSDT",
      "lastPrice": "0.00000000"
    },
    {
      "symbol": "UFTUSDT",
      "lastPrice": "0.00000000"
    },
    {
      "symbol": "LOOMUSDT",
      "lastPrice": "0.00000000"
    },
    {
      "symbol": "OAXUSDT",
      "lastPrice": "0.00000000"
    },
    {
      "symbol": "AERGOUSDT",
      "lastPrice": "0.00000000"
    },
    {
      "symbol": "ASTUSDT",
      "lastPrice": "0.00000000"
    },
    {
      "symbol": "SNTUSDT",
      "lastPrice": "0.00000000"
    },
    {
      "symbol": "COMBOUSDT",
      "lastPrice": "0.00000000"
    },
    {
      "symbol": "FDUSDUSDT",
      "lastPrice": "0.99770000"
    },
    {
      "symbol": "CREAMUSDT",
      "lastPrice": "0.00000000"
    },
    {
      "symbol": "GFTUSDT",
      "lastPrice": "0.00000000"
    },
    {
      "symbol": "PDAUSDT",
      "lastPrice": "0.00000000"
    },
    {
      "symbol": "BBUSDT",
      "lastPrice": "0.11720000"
    },
    {
      "symbol": "MOVEUSDT",
      "lastPrice": "0.13700000"
    },
    {
      "symbol": "USD1USDT",
      "lastPrice": "0.99930000"
    },
    {
      "symbol": "BFUSDUSDT",
      "lastPrice": "0.99940000"
    },
    {
      "symbol": "USDCUSDT",
      "lastPrice": "0.99930000"
    },
    {
      "symbol": "USDPUSDT",
      "lastPrice": "0.99930000"
    },
    {
      "symbol": "ETCUSDT",
      "lastPrice": "22.35000000"
    },
    {
      "symbol": "MEMEUSDT",
      "lastPrice": "0.00194300"
    },
    {
      "symbol": "BELUSDT",
      "lastPrice": "0.25860000"
    },
    {
      "symbol": "GUSDT",
      "lastPrice": "0.01205000"
    },
    {
      "symbol": "SPELLUSDT",
      "lastPrice": "0.00049320"
    },
    {
      "symbol": "RLCUSDT",
      "lastPrice": "0.95800000"
    },
    {
      "symbol": "BIGTIMEUSDT",
      "lastPrice": "0.05721000"
    },
    {
      "symbol": "PARTIUSDT",
      "lastPrice": "0.18510000"
    },
    {
      "symbol": "AWEUSDT",
      "lastPrice": "0.05182000"
    },
    {
      "symbol": "ALICEUSDT",
      "lastPrice": "0.38890000"
    },
    {
      "symbol": "TUTUSDT",
      "lastPrice": "0.05988000"
    },
    {
      "symbol": "SIGNUSDT",
      "lastPrice": "0.06972000"
    },
    {
      "symbol": "EDUUSDT",
      "lastPrice": "0.13560000"
    },
    {
      "symbol": "MBOXUSDT",
      "lastPrice": "0.05870000"
    },
    {
      "symbol": "ONGUSDT",
      "lastPrice": "0.17060000"
    },
    {
      "symbol": "PIVXUSDT",
      "lastPrice": "0.14470000"
    },
    {
      "symbol": "PAXGUSDT",
      "lastPrice": "3330.94000000"
    },
    {
      "symbol": "STORJUSDT",
      "lastPrice": "0.26420000"
    },
    {
      "symbol": "PONDUSDT",
      "lastPrice": "0.00800000"
    },
    {
      "symbol": "RDNTUSDT",
      "lastPrice": "0.02228000"
    },
    {
      "symbol": "HMSTRUSDT",
      "lastPrice": "0.00074000"
    },
    {
      "symbol": "TIAUSDT",
      "lastPrice": "1.78900000"
    },
    {
      "symbol": "TWTUSDT",
      "lastPrice": "0.78200000"
    },
    {
      "symbol": "WAXPUSDT",
      "lastPrice": "0.02091000"
    },
    {
      "symbol": "YFIUSDT",
      "lastPrice": "5636.00000000"
    },
    {
      "symbol": "BANANAS31USDT",
      "lastPrice": "0.00687500"
    },
    {
      "symbol": "FLMUSDT",
      "lastPrice": "0.02920000"
    },
    {
      "symbol": "KAITOUSDT",
      "lastPrice": "1.07490000"
    },
    {
      "symbol": "NMRUSDT",
      "lastPrice": "8.51000000"
    },
    {
      "symbol": "ACMUSDT",
      "lastPrice": "1.13000000"
    },
    {
      "symbol": "ANKRUSDT",
      "lastPrice": "0.01584000"
    },
    {
      "symbol": "FIOUSDT",
      "lastPrice": "0.01806000"
    },
    {
      "symbol": "XAIUSDT",
      "lastPrice": "0.05030000"
    },
    {
      "symbol": "FILUSDT",
      "lastPrice": "2.50100000"
    },
    {
      "symbol": "TUSDT",
      "lastPrice": "0.01663000"
    },
    {
      "symbol": "ZILUSDT",
      "lastPrice": "0.01139000"
    },
    {
      "symbol": "DODOUSDT",
      "lastPrice": "0.04440000"
    },
    {
      "symbol": "MASKUSDT",
      "lastPrice": "1.29800000"
    },
    {
      "symbol": "ARKUSDT",
      "lastPrice": "0.44260000"
    },
    {
      "symbol": "PNUTUSDT",
      "lastPrice": "0.22910000"
    },
    {
      "symbol": "SYRUPUSDT",
      "lastPrice": "0.43210000"
    },
    {
      "symbol": "DENTUSDT",
      "lastPrice": "0.00079500"
    },
    {
      "symbol": "RPLUSDT",
      "lastPrice": "7.77000000"
    },
    {
      "symbol": "UNIUSDT",
      "lastPrice": "10.95300000"
    },
    {
      "symbol": "TOWNSUSDT",
      "lastPrice": "0.03028000"
    },
    {
      "symbol": "CHRUSDT",
      "lastPrice": "0.09390000"
    },
    {
      "symbol": "BCHUSDT",
      "lastPrice": "591.80000000"
    },
    {
      "symbol": "MTLUSDT",
      "lastPrice": "0.73500000"
    },
    {
      "symbol": "DUSDT",
      "lastPrice": "0.03432000"
    },
    {
      "symbol": "HOOKUSDT",
      "lastPrice": "0.10640000"
    },
    {
      "symbol": "KNCUSDT",
      "lastPrice": "0.40650000"
    },
    {
      "symbol": "QNTUSDT",
      "lastPrice": "110.18000000"
    },
    {
      "symbol": "TLMUSDT",
      "lastPrice": "0.00484000"
    },
    {
      "symbol": "COWUSDT",
      "lastPrice": "0.38540000"
    },
    {
      "symbol": "CGPTUSDT",
      "lastPrice": "0.09480000"
    },
    {
      "symbol": "ATOMUSDT",
      "lastPrice": "4.51300000"
    },
    {
      "symbol": "POWRUSDT",
      "lastPrice": "0.16930000"
    },
    {
      "symbol": "PYTHUSDT",
      "lastPrice": "0.12240000"
    },
    {
      "symbol": "MEUSDT",
      "lastPrice": "0.71700000"
    },
    {
      "symbol": "AUCTIONUSDT",
      "lastPrice": "10.02000000"
    },
    {
      "symbol": "STXUSDT",
      "lastPrice": "0.71300000"
    },
    {
      "symbol": "LISTAUSDT",
      "lastPrice": "0.28400000"
    },
    {
      "symbol": "PIXELUSDT",
      "lastPrice": "0.03402000"
    },
    {
      "symbol": "ACEUSDT",
      "lastPrice": "0.54600000"
    },
    {
      "symbol": "ARDRUSDT",
      "lastPrice": "0.09532000"
    },
    {
      "symbol": "SLPUSDT",
      "lastPrice": "0.00186100"
    },
    {
      "symbol": "AMPUSDT",
      "lastPrice": "0.00358900"
    },
    {
      "symbol": "DCRUSDT",
      "lastPrice": "17.24000000"
    },
    {
      "symbol": "SXPUSDT",
      "lastPrice": "0.18210000"
    },
    {
      "symbol": "FLOWUSDT",
      "lastPrice": "0.38900000"
    },
    {
      "symbol": "XVSUSDT",
      "lastPrice": "6.20000000"
    },
    {
      "symbol": "ONTUSDT",
      "lastPrice": "0.13570000"
    },
    {
      "symbol": "DYMUSDT",
      "lastPrice": "0.24600000"
    },
    {
      "symbol": "FTTUSDT",
      "lastPrice": "0.91650000"
    },
    {
      "symbol": "ICPUSDT",
      "lastPrice": "5.47100000"
    },
    {
      "symbol": "HBARUSDT",
      "lastPrice": "0.25206000"
    },
    {
      "symbol": "IQUSDT",
      "lastPrice": "0.00351700"
    },
    {
      "symbol": "ORCAUSDT",
      "lastPrice": "2.41500000"
    },
    {
      "symbol": "ANIMEUSDT",
      "lastPrice": "0.01810000"
    },
    {
      "symbol": "SOLVUSDT",
      "lastPrice": "0.04313000"
    },
    {
      "symbol": "FARMUSDT",
      "lastPrice": "29.76000000"
    },
    {
      "symbol": "PHBUSDT",
      "lastPrice": "0.56900000"
    },
    {
      "symbol": "CAKEUSDT",
      "lastPrice": "2.72200000"
    },
    {
      "symbol": "SYSUSDT",
      "lastPrice": "0.04291000"
    },
    {
      "symbol": "RONINUSDT",
      "lastPrice": "0.55800000"
    },
    {
      "symbol": "GMTUSDT",
      "lastPrice": "0.04370000"
    },
    {
      "symbol": "KERNELUSDT",
      "lastPrice": "0.20680000"
    },
    {
      "symbol": "BTCUSDT",
      "lastPrice": "117652.00000000"
    },
    {
      "symbol": "WBTCUSDT",
      "lastPrice": "117644.50000000"
    },
    {
      "symbol": "MINAUSDT",
      "lastPrice": "0.19030000"
    },
    {
      "symbol": "AVAUSDT",
      "lastPrice": "0.57000000"
    },
    {
      "symbol": "MOVRUSDT",
      "lastPrice": "6.49600000"
    },
    {
      "symbol": "LSKUSDT",
      "lastPrice": "0.40600000"
    },
    {
      "symbol": "ENAUSDT",
      "lastPrice": "0.71960000"
    },
    {
      "symbol": "AUSDT",
      "lastPrice": "0.50970000"
    },
    {
      "symbol": "ALGOUSDT",
      "lastPrice": "0.25720000"
    },
    {
      "symbol": "ZENUSDT",
      "lastPrice": "7.88000000"
    },
    {
      "symbol": "STRAXUSDT",
      "lastPrice": "0.04753000"
    },
    {
      "symbol": "CETUSUSDT",
      "lastPrice": "0.10520000"
    },
    {
      "symbol": "CVCUSDT",
      "lastPrice": "0.09460000"
    },
    {
      "symbol": "HIGHUSDT",
      "lastPrice": "0.56600000"
    },
    {
      "symbol": "NTRNUSDT",
      "lastPrice": "0.09200000"
    },
    {
      "symbol": "ARUSDT",
      "lastPrice": "7.35000000"
    },
    {
      "symbol": "VETUSDT",
      "lastPrice": "0.02462000"
    },
    {
      "symbol": "TURBOUSDT",
      "lastPrice": "0.00441100"
    },
    {
      "symbol": "ICXUSDT",
      "lastPrice": "0.13280000"
    },
    {
      "symbol": "AIUSDT",
      "lastPrice": "0.12370000"
    },
    {
      "symbol": "PHAUSDT",
      "lastPrice": "0.10590000"
    },
    {
      "symbol": "TRBUSDT",
      "lastPrice": "37.03000000"
    },
    {
      "symbol": "C98USDT",
      "lastPrice": "0.05270000"
    },
    {
      "symbol": "ATMUSDT",
      "lastPrice": "1.56300000"
    },
    {
      "symbol": "NXPCUSDT",
      "lastPrice": "0.86550000"
    },
    {
      "symbol": "CKBUSDT",
      "lastPrice": "0.00518400"
    },
    {
      "symbol": "IDUSDT",
      "lastPrice": "0.16270000"
    },
    {
      "symbol": "WOOUSDT",
      "lastPrice": "0.07680000"
    },
    {
      "symbol": "BMTUSDT",
      "lastPrice": "0.07620000"
    },
    {
      "symbol": "DOTUSDT",
      "lastPrice": "3.95900000"
    },
    {
      "symbol": "SAGAUSDT",
      "lastPrice": "0.25800000"
    },
    {
      "symbol": "SSVUSDT",
      "lastPrice": "9.07000000"
    },
    {
      "symbol": "PROMUSDT",
      "lastPrice": "8.90000000"
    },
    {
      "symbol": "AEVOUSDT",
      "lastPrice": "0.09710000"
    },
    {
      "symbol": "MAGICUSDT",
      "lastPrice": "0.24760000"
    },
    {
      "symbol": "1INCHUSDT",
      "lastPrice": "0.25520000"
    },
    {
      "symbol": "UTKUSDT",
      "lastPrice": "0.03027000"
    },
    {
      "symbol": "VANRYUSDT",
      "lastPrice": "0.03140000"
    },
    {
      "symbol": "DIAUSDT",
      "lastPrice": "0.76790000"
    },
    {
      "symbol": "FETUSDT",
      "lastPrice": "0.70400000"
    },
    {
      "symbol": "TRXUSDT",
      "lastPrice": "0.35400000"
    },
    {
      "symbol": "PEOPLEUSDT",
      "lastPrice": "0.01905000"
    },
    {
      "symbol": "SUSDT",
      "lastPrice": "0.30480000"
    },
    {
      "symbol": "POLYXUSDT",
      "lastPrice": "0.13690000"
    },
    {
      "symbol": "SCRTUSDT",
      "lastPrice": "0.17980000"
    },
    {
      "symbol": "LPTUSDT",
      "lastPrice": "6.49700000"
    },
    {
      "symbol": "BROCCOLI714USDT",
      "lastPrice": "0.02534000"
    },
    {
      "symbol": "LAYERUSDT",
      "lastPrice": "0.60470000"
    },
    {
      "symbol": "ENSUSDT",
      "lastPrice": "26.46000000"
    },
    {
      "symbol": "TREEUSDT",
      "lastPrice": "0.36180000"
    },
    {
      "symbol": "EGLDUSDT",
      "lastPrice": "15.17000000"
    },
    {
      "symbol": "NILUSDT",
      "lastPrice": "0.29600000"
    },
    {
      "symbol": "SANTOSUSDT",
      "lastPrice": "2.59800000"
    },
    {
      "symbol": "ACXUSDT",
      "lastPrice": "0.18000000"
    },
    {
      "symbol": "IMXUSDT",
      "lastPrice": "0.57500000"
    },
    {
      "symbol": "QUICKUSDT",
      "lastPrice": "0.02339000"
    },
    {
      "symbol": "AGLDUSDT",
      "lastPrice": "0.70900000"
    },
    {
      "symbol": "BAKEUSDT",
      "lastPrice": "0.08440000"
    },
    {
      "symbol": "VOXELUSDT",
      "lastPrice": "0.05620000"
    },
    {
      "symbol": "NKNUSDT",
      "lastPrice": "0.02790000"
    },
    {
      "symbol": "YGGUSDT",
      "lastPrice": "0.15980000"
    },
    {
      "symbol": "VICUSDT",
      "lastPrice": "0.24290000"
    },
    {
      "symbol": "STGUSDT",
      "lastPrice": "0.17290000"
    },
    {
      "symbol": "ASTRUSDT",
      "lastPrice": "0.02470000"
    },
    {
      "symbol": "PEPEUSDT",
      "lastPrice": "0.00001094"
    },
    {
      "symbol": "ONEUSDT",
      "lastPrice": "0.01084000"
    },
    {
      "symbol": "BTTCUSDT",
      "lastPrice": "0.00000067"
    },
    {
      "symbol": "BONKUSDT",
      "lastPrice": "0.00002404"
    },
    {
      "symbol": "DYDXUSDT",
      "lastPrice": "0.65710000"
    },
    {
      "symbol": "BOMEUSDT",
      "lastPrice": "0.00184500"
    },
    {
      "symbol": "HIVEUSDT",
      "lastPrice": "0.21650000"
    },
    {
      "symbol": "TFUELUSDT",
      "lastPrice": "0.03657000"
    },
    {
      "symbol": "TRUUSDT",
      "lastPrice": "0.03250000"
    },
    {
      "symbol": "XVGUSDT",
      "lastPrice": "0.00659800"
    },
    {
      "symbol": "QIUSDT",
      "lastPrice": "0.00710000"
    },
    {
      "symbol": "CITYUSDT",
      "lastPrice": "1.21700000"
    },
    {
      "symbol": "WLDUSDT",
      "lastPrice": "0.99000000"
    },
    {
      "symbol": "KDAUSDT",
      "lastPrice": "0.40460000"
    },
    {
      "symbol": "APTUSDT",
      "lastPrice": "4.70300000"
    },
    {
      "symbol": "DATAUSDT",
      "lastPrice": "0.01638000"
    },
    {
      "symbol": "BNBUSDT",
      "lastPrice": "834.38000000"
    },
    {
      "symbol": "POLUSDT",
      "lastPrice": "0.23530000"
    },
    {
      "symbol": "OMUSDT",
      "lastPrice": "0.25310000"
    },
    {
      "symbol": "XNOUSDT",
      "lastPrice": "0.96400000"
    },
    {
      "symbol": "GHSTUSDT",
      "lastPrice": "0.47800000"
    },
    {
      "symbol": "COSUSDT",
      "lastPrice": "0.00334100"
    },
    {
      "symbol": "COMPUSDT",
      "lastPrice": "47.73000000"
    },
    {
      "symbol": "PSGUSDT",
      "lastPrice": "1.90900000"
    },
    {
      "symbol": "LTCUSDT",
      "lastPrice": "118.91000000"
    },
    {
      "symbol": "BLURUSDT",
      "lastPrice": "0.08070000"
    },
    {
      "symbol": "1MBABYDOGEUSDT",
      "lastPrice": "0.00130160"
    },
    {
      "symbol": "NFPUSDT",
      "lastPrice": "0.06880000"
    },
    {
      "symbol": "OSMOUSDT",
      "lastPrice": "0.17470000"
    },
    {
      "symbol": "IOUSDT",
      "lastPrice": "0.61700000"
    },
    {
      "symbol": "ADXUSDT",
      "lastPrice": "0.14400000"
    },
    {
      "symbol": "1000CATUSDT",
      "lastPrice": "0.00824000"
    },
    {
      "symbol": "NEIROUSDT",
      "lastPrice": "0.00038177"
    },
    {
      "symbol": "WCTUSDT",
      "lastPrice": "0.32240000"
    },
    {
      "symbol": "VIRTUALUSDT",
      "lastPrice": "1.19680000"
    },
    {
      "symbol": "1000SATSUSDT",
      "lastPrice": "0.00003896"
    },
    {
      "symbol": "METISUSDT",
      "lastPrice": "17.07000000"
    },
    {
      "symbol": "SUPERUSDT",
      "lastPrice": "0.70770000"
    },
    {
      "symbol": "SOPHUSDT",
      "lastPrice": "0.03648000"
    },
    {
      "symbol": "COTIUSDT",
      "lastPrice": "0.05402000"
    },
    {
      "symbol": "CVXUSDT",
      "lastPrice": "4.14800000"
    },
    {
      "symbol": "HAEDALUSDT",
      "lastPrice": "0.13210000"
    },
    {
      "symbol": "AIXBTUSDT",
      "lastPrice": "0.11660000"
    },
    {
      "symbol": "FXSUSDT",
      "lastPrice": "2.75900000"
    },
    {
      "symbol": "SPKUSDT",
      "lastPrice": "0.08417600"
    },
    {
      "symbol": "PERPUSDT",
      "lastPrice": "0.27280000"
    },
    {
      "symbol": "JOEUSDT",
      "lastPrice": "0.15850000"
    },
    {
      "symbol": "MUBARAKUSDT",
      "lastPrice": "0.03365000"
    },
    {
      "symbol": "TAOUSDT",
      "lastPrice": "370.60000000"
    },
    {
      "symbol": "JTOUSDT",
      "lastPrice": "1.76900000"
    },
    {
      "symbol": "SFPUSDT",
      "lastPrice": "0.47480000"
    },
    {
      "symbol": "RSRUSDT",
      "lastPrice": "0.00903900"
    },
    {
      "symbol": "IOSTUSDT",
      "lastPrice": "0.00358200"
    },
    {
      "symbol": "ZROUSDT",
      "lastPrice": "2.10800000"
    },
    {
      "symbol": "CELOUSDT",
      "lastPrice": "0.33670000"
    },
    {
      "symbol": "QKCUSDT",
      "lastPrice": "0.00731500"
    },
    {
      "symbol": "JSTUSDT",
      "lastPrice": "0.03333000"
    },
    {
      "symbol": "SAHARAUSDT",
      "lastPrice": "0.09239000"
    },
    {
      "symbol": "DUSKUSDT",
      "lastPrice": "0.06350000"
    },
    {
      "symbol": "WUSDT",
      "lastPrice": "0.08060000"
    },
    {
      "symbol": "NEARUSDT",
      "lastPrice": "2.72600000"
    },
    {
      "symbol": "ONDOUSDT",
      "lastPrice": "0.99250000"
    },
    {
      "symbol": "DGBUSDT",
      "lastPrice": "0.00913000"
    },
    {
      "symbol": "RUNEUSDT",
      "lastPrice": "1.36500000"
    },
    {
      "symbol": "NEXOUSDT",
      "lastPrice": "1.35500000"
    },
    {
      "symbol": "PUNDIXUSDT",
      "lastPrice": "0.30480000"
    },
    {
      "symbol": "SUSHIUSDT",
      "lastPrice": "0.82600000"
    },
    {
      "symbol": "CYBERUSDT",
      "lastPrice": "2.42300000"
    },
    {
      "symbol": "GMXUSDT",
      "lastPrice": "15.32000000"
    },
    {
      "symbol": "JUPUSDT",
      "lastPrice": "0.51260000"
    },
    {
      "symbol": "BNTUSDT",
      "lastPrice": "0.77380000"
    },
    {
      "symbol": "BICOUSDT",
      "lastPrice": "0.10720000"
    },
    {
      "symbol": "SUNUSDT",
      "lastPrice": "0.02391000"
    },
    {
      "symbol": "LINKUSDT",
      "lastPrice": "21.80000000"
    },
    {
      "symbol": "REIUSDT",
      "lastPrice": "0.01827000"
    },
    {
      "symbol": "KSMUSDT",
      "lastPrice": "14.98000000"
    },
    {
      "symbol": "AXLUSDT",
      "lastPrice": "0.33580000"
    },
    {
      "symbol": "MANTAUSDT",
      "lastPrice": "0.22600000"
    },
    {
      "symbol": "SUIUSDT",
      "lastPrice": "3.74100000"
    },
    {
      "symbol": "USUALUSDT",
      "lastPrice": "0.07060000"
    },
    {
      "symbol": "IOTXUSDT",
      "lastPrice": "0.02890000"
    },
    {
      "symbol": "BEAMXUSDT",
      "lastPrice": "0.00769000"
    },
    {
      "symbol": "KAIAUSDT",
      "lastPrice": "0.15360000"
    },
    {
      "symbol": "RESOLVUSDT",
      "lastPrice": "0.16580000"
    },
    {
      "symbol": "PENGUUSDT",
      "lastPrice": "0.03272000"
    },
    {
      "symbol": "ENJUSDT",
      "lastPrice": "0.06910000"
    },
    {
      "symbol": "PORTALUSDT",
      "lastPrice": "0.04480000"
    },
    {
      "symbol": "HEIUSDT",
      "lastPrice": "0.45490000"
    },
    {
      "symbol": "ALCXUSDT",
      "lastPrice": "10.40000000"
    },
    {
      "symbol": "ROSEUSDT",
      "lastPrice": "0.02790000"
    },
    {
      "symbol": "ZKUSDT",
      "lastPrice": "0.06251000"
    },
    {
      "symbol": "PENDLEUSDT",
      "lastPrice": "5.35500000"
    },
    {
      "symbol": "FIDAUSDT",
      "lastPrice": "0.09820000"
    },
    {
      "symbol": "HFTUSDT",
      "lastPrice": "0.08590000"
    },
    {
      "symbol": "BIFIUSDT",
      "lastPrice": "195.70000000"
    },
    {
      "symbol": "OGUSDT",
      "lastPrice": "14.92900000"
    },
    {
      "symbol": "RAYUSDT",
      "lastPrice": "3.54800000"
    },
    {
      "symbol": "REZUSDT",
      "lastPrice": "0.01339000"
    },
    {
      "symbol": "MKRUSDT",
      "lastPrice": "1811.10000000"
    },
    {
      "symbol": "BNSOLUSDT",
      "lastPrice": "201.00000000"
    },
    {
      "symbol": "SOLUSDT",
      "lastPrice": "188.06000000"
    },
    {
      "symbol": "SCRUSDT",
      "lastPrice": "0.37500000"
    },
    {
      "symbol": "ARKMUSDT",
      "lastPrice": "0.55400000"
    },
    {
      "symbol": "WBETHUSDT",
      "lastPrice": "4785.77000000"
    },
    {
      "symbol": "VELODROMEUSDT",
      "lastPrice": "0.05590000"
    },
    {
      "symbol": "LQTYUSDT",
      "lastPrice": "0.91300000"
    },
    {
      "symbol": "ETHUSDT",
      "lastPrice": "4451.66000000"
    },
    {
      "symbol": "FLUXUSDT",
      "lastPrice": "0.20820000"
    },
    {
      "symbol": "MAVUSDT",
      "lastPrice": "0.05214000"
    },
    {
      "symbol": "SEIUSDT",
      "lastPrice": "0.32230000"
    },
    {
      "symbol": "OPUSDT",
      "lastPrice": "0.72500000"
    },
    {
      "symbol": "KMNOUSDT",
      "lastPrice": "0.05967000"
    },
    {
      "symbol": "AVAXUSDT",
      "lastPrice": "23.93000000"
    },
    {
      "symbol": "JASMYUSDT",
      "lastPrice": "0.01637000"
    },
    {
      "symbol": "SHELLUSDT",
      "lastPrice": "0.13490000"
    },
    {
      "symbol": "INJUSDT",
      "lastPrice": "14.41000000"
    },
    {
      "symbol": "CUSDT",
      "lastPrice": "0.22620000"
    },
    {
      "symbol": "ZECUSDT",
      "lastPrice": "36.63000000"
    },
    {
      "symbol": "BANANAUSDT",
      "lastPrice": "23.93000000"
    },
    {
      "symbol": "WIFUSDT",
      "lastPrice": "0.88400000"
    },
    {
      "symbol": "GPSUSDT",
      "lastPrice": "0.01429000"
    },
    {
      "symbol": "BABYUSDT",
      "lastPrice": "0.05718000"
    },
    {
      "symbol": "CHESSUSDT",
      "lastPrice": "0.07240000"
    },
    {
      "symbol": "HOMEUSDT",
      "lastPrice": "0.04432000"
    },
    {
      "symbol": "A2ZUSDT",
      "lastPrice": "0.00605800"
    },
    {
      "symbol": "BIOUSDT",
      "lastPrice": "0.09860000"
    },
    {
      "symbol": "ETHFIUSDT",
      "lastPrice": "1.14200000"
    },
    {
      "symbol": "GNOUSDT",
      "lastPrice": "137.99000000"
    },
    {
      "symbol": "INITUSDT",
      "lastPrice": "0.40380000"
    },
    {
      "symbol": "AAVEUSDT",
      "lastPrice": "294.14000000"
    },
    {
      "symbol": "WANUSDT",
      "lastPrice": "0.11890000"
    },
    {
      "symbol": "TKOUSDT",
      "lastPrice": "0.17450000"
    },
    {
      "symbol": "ARBUSDT",
      "lastPrice": "0.48390000"
    },
    {
      "symbol": "EIGENUSDT",
      "lastPrice": "1.34400000"
    },
    {
      "symbol": "CRVUSDT",
      "lastPrice": "0.85910000"
    },
    {
      "symbol": "GTCUSDT",
      "lastPrice": "0.35000000"
    },
    {
      "symbol": "ASRUSDT",
      "lastPrice": "4.69800000"
    },
    {
      "symbol": "IDEXUSDT",
      "lastPrice": "0.02710000"
    },
    {
      "symbol": "JUVUSDT",
      "lastPrice": "1.51400000"
    },
    {
      "symbol": "SLFUSDT",
      "lastPrice": "0.06300000"
    },
    {
      "symbol": "MDTUSDT",
      "lastPrice": "0.03067000"
    },
    {
      "symbol": "SKLUSDT",
      "lastPrice": "0.03488000"
    },
    {
      "symbol": "ALPHAUSDT",
      "lastPrice": "0.00970000"
    },
    {
      "symbol": "BSWUSDT",
      "lastPrice": "0.01120000"
    },
    {
      "symbol": "LEVERUSDT",
      "lastPrice": "0.00017500"
    },
    {
      "symbol": "KMDUSDT",
      "lastPrice": "0.01630000"
    },
    {
      "symbol": "LTOUSDT",
      "lastPrice": "0.00380000"
    }
  ]
}