{
  "lastUpdated": "2025-08-13T15:49:50.266Z",
  "marketSentiment": 58.069883527454245,
  "ethChange": 4.734,
  "topGainers": [
    {
      "symbol": "GTCUSDT",
      "lastPrice": "0.49200000",
      "priceChangePercent": "59.223"
    },
    {
      "symbol": "SKLUSDT",
      "lastPrice": "0.02824000",
      "priceChangePercent": "32.707"
    },
    {
      "symbol": "ZKUSDT",
      "lastPrice": "0.06915000",
      "priceChangePercent": "17.622"
    },
    {
      "symbol": "ARBUSDT",
      "lastPrice": "0.53860000",
      "priceChangePercent": "15.654"
    },
    {
      "symbol": "THEUSDT",
      "lastPrice": "0.43550000",
      "priceChangePercent": "14.515"
    },
    {
      "symbol": "KMNOUSDT",
      "lastPrice": "0.06159000",
      "priceChangePercent": "14.204"
    },
    {
      "symbol": "RAYUSDT",
      "lastPrice": "3.65900000",
      "priceChangePercent": "13.740"
    },
    {
      "symbol": "BOMEUSDT",
      "lastPrice": "0.00214000",
      "priceChangePercent": "11.633"
    },
    {
      "symbol": "EIGENUSDT",
      "lastPrice": "1.56100000",
      "priceChangePercent": "11.262"
    },
    {
      "symbol": "STRKUSDT",
      "lastPrice": "0.14940000",
      "priceChangePercent": "11.161"
    },
    {
      "symbol": "SEIUSDT",
      "lastPrice": "0.35020000",
      "priceChangePercent": "10.578"
    },
    {
      "symbol": "DYDXUSDT",
      "lastPrice": "0.73660000",
      "priceChangePercent": "10.352"
    },
    {
      "symbol": "NTRNUSDT",
      "lastPrice": "0.10260000",
      "priceChangePercent": "10.323"
    },
    {
      "symbol": "ROSEUSDT",
      "lastPrice": "0.03146000",
      "priceChangePercent": "10.038"
    },
    {
      "symbol": "MLNUSDT",
      "lastPrice": "9.32000000",
      "priceChangePercent": "9.518"
    },
    {
      "symbol": "COTIUSDT",
      "lastPrice": "0.06013000",
      "priceChangePercent": "9.506"
    },
    {
      "symbol": "BNSOLUSDT",
      "lastPrice": "211.10000000",
      "priceChangePercent": "9.208"
    },
    {
      "symbol": "SOLUSDT",
      "lastPrice": "197.55000000",
      "priceChangePercent": "9.053"
    },
    {
      "symbol": "PEOPLEUSDT",
      "lastPrice": "0.02201000",
      "priceChangePercent": "9.014"
    },
    {
      "symbol": "SUSHIUSDT",
      "lastPrice": "0.92700000",
      "priceChangePercent": "8.931"
    }
  ],
  "allTickers": [
    {
      "symbol": "GTCUSDT",
      "lastPrice": "0.49200000"
    },
    {
      "symbol": "SKLUSDT",
      "lastPrice": "0.02824000"
    },
    {
      "symbol": "ZKUSDT",
      "lastPrice": "0.06915000"
    },
    {
      "symbol": "ARBUSDT",
      "lastPrice": "0.53860000"
    },
    {
      "symbol": "THEUSDT",
      "lastPrice": "0.43550000"
    },
    {
      "symbol": "KMNOUSDT",
      "lastPrice": "0.06159000"
    },
    {
      "symbol": "RAYUSDT",
      "lastPrice": "3.65900000"
    },
    {
      "symbol": "BOMEUSDT",
      "lastPrice": "0.00214000"
    },
    {
      "symbol": "EIGENUSDT",
      "lastPrice": "1.56100000"
    },
    {
      "symbol": "STRKUSDT",
      "lastPrice": "0.14940000"
    },
    {
      "symbol": "SEIUSDT",
      "lastPrice": "0.35020000"
    },
    {
      "symbol": "DYDXUSDT",
      "lastPrice": "0.73660000"
    },
    {
      "symbol": "NTRNUSDT",
      "lastPrice": "0.10260000"
    },
    {
      "symbol": "ROSEUSDT",
      "lastPrice": "0.03146000"
    },
    {
      "symbol": "MLNUSDT",
      "lastPrice": "9.32000000"
    },
    {
      "symbol": "COTIUSDT",
      "lastPrice": "0.06013000"
    },
    {
      "symbol": "BNSOLUSDT",
      "lastPrice": "211.10000000"
    },
    {
      "symbol": "SOLUSDT",
      "lastPrice": "197.55000000"
    },
    {
      "symbol": "PEOPLEUSDT",
      "lastPrice": "0.02201000"
    },
    {
      "symbol": "SUSHIUSDT",
      "lastPrice": "0.92700000"
    },
    {
      "symbol": "WIFUSDT",
      "lastPrice": "1.03300000"
    },
    {
      "symbol": "OGUSDT",
      "lastPrice": "15.09100000"
    },
    {
      "symbol": "IOUSDT",
      "lastPrice": "0.68700000"
    },
    {
      "symbol": "SIGNUSDT",
      "lastPrice": "0.07551000"
    },
    {
      "symbol": "LOKAUSDT",
      "lastPrice": "0.12370000"
    },
    {
      "symbol": "ONEUSDT",
      "lastPrice": "0.01200000"
    },
    {
      "symbol": "TIAUSDT",
      "lastPrice": "1.95400000"
    },
    {
      "symbol": "FIDAUSDT",
      "lastPrice": "0.11070000"
    },
    {
      "symbol": "HOMEUSDT",
      "lastPrice": "0.04540000"
    },
    {
      "symbol": "DGBUSDT",
      "lastPrice": "0.00962000"
    },
    {
      "symbol": "HOOKUSDT",
      "lastPrice": "0.12010000"
    },
    {
      "symbol": "MEMEUSDT",
      "lastPrice": "0.00191900"
    },
    {
      "symbol": "VANRYUSDT",
      "lastPrice": "0.03520000"
    },
    {
      "symbol": "INJUSDT",
      "lastPrice": "15.54000000"
    },
    {
      "symbol": "ADAUSDT",
      "lastPrice": "0.87110000"
    },
    {
      "symbol": "ENJUSDT",
      "lastPrice": "0.07790000"
    },
    {
      "symbol": "LRCUSDT",
      "lastPrice": "0.09630000"
    },
    {
      "symbol": "OPUSDT",
      "lastPrice": "0.83600000"
    },
    {
      "symbol": "FLOWUSDT",
      "lastPrice": "0.41000000"
    },
    {
      "symbol": "WOOUSDT",
      "lastPrice": "0.08460000"
    },
    {
      "symbol": "ARUSDT",
      "lastPrice": "8.19000000"
    },
    {
      "symbol": "TRUMPUSDT",
      "lastPrice": "9.61000000"
    },
    {
      "symbol": "GUSDT",
      "lastPrice": "0.01307000"
    },
    {
      "symbol": "WCTUSDT",
      "lastPrice": "0.34830000"
    },
    {
      "symbol": "ETHFIUSDT",
      "lastPrice": "1.29700000"
    },
    {
      "symbol": "NEARUSDT",
      "lastPrice": "2.90600000"
    },
    {
      "symbol": "GLMRUSDT",
      "lastPrice": "0.08000000"
    },
    {
      "symbol": "CTSIUSDT",
      "lastPrice": "0.07600000"
    },
    {
      "symbol": "AUSDT",
      "lastPrice": "0.57680000"
    },
    {
      "symbol": "TWTUSDT",
      "lastPrice": "0.82650000"
    },
    {
      "symbol": "CELRUSDT",
      "lastPrice": "0.00866000"
    },
    {
      "symbol": "SUPERUSDT",
      "lastPrice": "0.82510000"
    },
    {
      "symbol": "AEVOUSDT",
      "lastPrice": "0.10750000"
    },
    {
      "symbol": "TRUUSDT",
      "lastPrice": "0.03490000"
    },
    {
      "symbol": "UNIUSDT",
      "lastPrice": "11.95500000"
    },
    {
      "symbol": "NILUSDT",
      "lastPrice": "0.33030000"
    },
    {
      "symbol": "GALAUSDT",
      "lastPrice": "0.01859000"
    },
    {
      "symbol": "DYMUSDT",
      "lastPrice": "0.27300000"
    },
    {
      "symbol": "ZILUSDT",
      "lastPrice": "0.01233000"
    },
    {
      "symbol": "BATUSDT",
      "lastPrice": "0.16040000"
    },
    {
      "symbol": "DOGEUSDT",
      "lastPrice": "0.24152000"
    },
    {
      "symbol": "SYSUSDT",
      "lastPrice": "0.04988000"
    },
    {
      "symbol": "EGLDUSDT",
      "lastPrice": "16.63000000"
    },
    {
      "symbol": "WAXPUSDT",
      "lastPrice": "0.02208000"
    },
    {
      "symbol": "ICPUSDT",
      "lastPrice": "5.90400000"
    },
    {
      "symbol": "ALCXUSDT",
      "lastPrice": "11.24000000"
    },
    {
      "symbol": "ARKMUSDT",
      "lastPrice": "0.56200000"
    },
    {
      "symbol": "ALPINEUSDT",
      "lastPrice": "1.39700000"
    },
    {
      "symbol": "JUPUSDT",
      "lastPrice": "0.54550000"
    },
    {
      "symbol": "KSMUSDT",
      "lastPrice": "16.35000000"
    },
    {
      "symbol": "MINAUSDT",
      "lastPrice": "0.20710000"
    },
    {
      "symbol": "AIUSDT",
      "lastPrice": "0.13830000"
    },
    {
      "symbol": "BANDUSDT",
      "lastPrice": "0.76300000"
    },
    {
      "symbol": "NFPUSDT",
      "lastPrice": "0.07680000"
    },
    {
      "symbol": "HMSTRUSDT",
      "lastPrice": "0.00081200"
    },
    {
      "symbol": "TLMUSDT",
      "lastPrice": "0.00536000"
    },
    {
      "symbol": "RENDERUSDT",
      "lastPrice": "4.13100000"
    },
    {
      "symbol": "MAVUSDT",
      "lastPrice": "0.06351000"
    },
    {
      "symbol": "ICXUSDT",
      "lastPrice": "0.14190000"
    },
    {
      "symbol": "OXTUSDT",
      "lastPrice": "0.05830000"
    },
    {
      "symbol": "YGGUSDT",
      "lastPrice": "0.17820000"
    },
    {
      "symbol": "PHAUSDT",
      "lastPrice": "0.11570000"
    },
    {
      "symbol": "RDNTUSDT",
      "lastPrice": "0.02450000"
    },
    {
      "symbol": "MANTAUSDT",
      "lastPrice": "0.24500000"
    },
    {
      "symbol": "FILUSDT",
      "lastPrice": "2.70100000"
    },
    {
      "symbol": "IMXUSDT",
      "lastPrice": "0.61500000"
    },
    {
      "symbol": "GRTUSDT",
      "lastPrice": "0.10280000"
    },
    {
      "symbol": "PUNDIXUSDT",
      "lastPrice": "0.33180000"
    },
    {
      "symbol": "KERNELUSDT",
      "lastPrice": "0.21070000"
    },
    {
      "symbol": "DUSKUSDT",
      "lastPrice": "0.07070000"
    },
    {
      "symbol": "USUALUSDT",
      "lastPrice": "0.08120000"
    },
    {
      "symbol": "SNXUSDT",
      "lastPrice": "0.71000000"
    },
    {
      "symbol": "AXSUSDT",
      "lastPrice": "2.59800000"
    },
    {
      "symbol": "C98USDT",
      "lastPrice": "0.05870000"
    },
    {
      "symbol": "TOWNSUSDT",
      "lastPrice": "0.03385000"
    },
    {
      "symbol": "ATAUSDT",
      "lastPrice": "0.05320000"
    },
    {
      "symbol": "LUMIAUSDT",
      "lastPrice": "0.36300000"
    },
    {
      "symbol": "AGLDUSDT",
      "lastPrice": "0.77000000"
    },
    {
      "symbol": "FTTUSDT",
      "lastPrice": "0.98830000"
    },
    {
      "symbol": "WBETHUSDT",
      "lastPrice": "5010.44000000"
    },
    {
      "symbol": "QTUMUSDT",
      "lastPrice": "2.27000000"
    },
    {
      "symbol": "ARPAUSDT",
      "lastPrice": "0.02432000"
    },
    {
      "symbol": "SUSDT",
      "lastPrice": "0.32690000"
    },
    {
      "symbol": "SCRTUSDT",
      "lastPrice": "0.19830000"
    },
    {
      "symbol": "PYTHUSDT",
      "lastPrice": "0.13230000"
    },
    {
      "symbol": "ETHUSDT",
      "lastPrice": "4656.99000000"
    },
    {
      "symbol": "JTOUSDT",
      "lastPrice": "1.92500000"
    },
    {
      "symbol": "ATOMUSDT",
      "lastPrice": "4.83200000"
    },
    {
      "symbol": "MANAUSDT",
      "lastPrice": "0.31700000"
    },
    {
      "symbol": "FLOKIUSDT",
      "lastPrice": "0.00011749"
    },
    {
      "symbol": "BAKEUSDT",
      "lastPrice": "0.09070000"
    },
    {
      "symbol": "1000SATSUSDT",
      "lastPrice": "0.00004321"
    },
    {
      "symbol": "ONTUSDT",
      "lastPrice": "0.14820000"
    },
    {
      "symbol": "LTCUSDT",
      "lastPrice": "130.25000000"
    },
    {
      "symbol": "CVXUSDT",
      "lastPrice": "4.67500000"
    },
    {
      "symbol": "NKNUSDT",
      "lastPrice": "0.03040000"
    },
    {
      "symbol": "VETUSDT",
      "lastPrice": "0.02624000"
    },
    {
      "symbol": "WLDUSDT",
      "lastPrice": "1.08000000"
    },
    {
      "symbol": "SXPUSDT",
      "lastPrice": "0.19570000"
    },
    {
      "symbol": "SANDUSDT",
      "lastPrice": "0.30680000"
    },
    {
      "symbol": "STORJUSDT",
      "lastPrice": "0.28790000"
    },
    {
      "symbol": "TNSRUSDT",
      "lastPrice": "0.14530000"
    },
    {
      "symbol": "BELUSDT",
      "lastPrice": "0.27660000"
    },
    {
      "symbol": "CRVUSDT",
      "lastPrice": "1.02250000"
    },
    {
      "symbol": "HIGHUSDT",
      "lastPrice": "0.62300000"
    },
    {
      "symbol": "REIUSDT",
      "lastPrice": "0.01949000"
    },
    {
      "symbol": "ALICEUSDT",
      "lastPrice": "0.42640000"
    },
    {
      "symbol": "JASMYUSDT",
      "lastPrice": "0.01846000"
    },
    {
      "symbol": "KDAUSDT",
      "lastPrice": "0.44460000"
    },
    {
      "symbol": "LPTUSDT",
      "lastPrice": "7.02700000"
    },
    {
      "symbol": "TRBUSDT",
      "lastPrice": "40.48000000"
    },
    {
      "symbol": "ORCAUSDT",
      "lastPrice": "2.67500000"
    },
    {
      "symbol": "SUNUSDT",
      "lastPrice": "0.02381000"
    },
    {
      "symbol": "ORDIUSDT",
      "lastPrice": "10.46000000"
    },
    {
      "symbol": "GLMUSDT",
      "lastPrice": "0.27200000"
    },
    {
      "symbol": "CHRUSDT",
      "lastPrice": "0.10140000"
    },
    {
      "symbol": "RESOLVUSDT",
      "lastPrice": "0.19440000"
    },
    {
      "symbol": "DENTUSDT",
      "lastPrice": "0.00087300"
    },
    {
      "symbol": "PHBUSDT",
      "lastPrice": "0.62400000"
    },
    {
      "symbol": "CVCUSDT",
      "lastPrice": "0.10000000"
    },
    {
      "symbol": "IOTXUSDT",
      "lastPrice": "0.03086000"
    },
    {
      "symbol": "TAOUSDT",
      "lastPrice": "392.60000000"
    },
    {
      "symbol": "NMRUSDT",
      "lastPrice": "9.32000000"
    },
    {
      "symbol": "ACXUSDT",
      "lastPrice": "0.19700000"
    },
    {
      "symbol": "APTUSDT",
      "lastPrice": "4.93800000"
    },
    {
      "symbol": "MTLUSDT",
      "lastPrice": "0.79200000"
    },
    {
      "symbol": "DODOUSDT",
      "lastPrice": "0.04870000"
    },
    {
      "symbol": "API3USDT",
      "lastPrice": "0.79600000"
    },
    {
      "symbol": "IOSTUSDT",
      "lastPrice": "0.00391100"
    },
    {
      "symbol": "WUSDT",
      "lastPrice": "0.09040000"
    },
    {
      "symbol": "COSUSDT",
      "lastPrice": "0.00360800"
    },
    {
      "symbol": "BLURUSDT",
      "lastPrice": "0.08930000"
    },
    {
      "symbol": "STXUSDT",
      "lastPrice": "0.76700000"
    },
    {
      "symbol": "ZRXUSDT",
      "lastPrice": "0.27000000"
    },
    {
      "symbol": "ANIMEUSDT",
      "lastPrice": "0.01853000"
    },
    {
      "symbol": "KAIAUSDT",
      "lastPrice": "0.15390000"
    },
    {
      "symbol": "SUIUSDT",
      "lastPrice": "3.94230000"
    },
    {
      "symbol": "NEOUSDT",
      "lastPrice": "6.72000000"
    },
    {
      "symbol": "AAVEUSDT",
      "lastPrice": "323.04000000"
    },
    {
      "symbol": "GMTUSDT",
      "lastPrice": "0.04850000"
    },
    {
      "symbol": "WANUSDT",
      "lastPrice": "0.13220000"
    },
    {
      "symbol": "VELODROMEUSDT",
      "lastPrice": "0.06240000"
    },
    {
      "symbol": "RIFUSDT",
      "lastPrice": "0.05970000"
    },
    {
      "symbol": "DUSDT",
      "lastPrice": "0.03778000"
    },
    {
      "symbol": "YFIUSDT",
      "lastPrice": "5980.00000000"
    },
    {
      "symbol": "WINUSDT",
      "lastPrice": "0.00006398"
    },
    {
      "symbol": "BBUSDT",
      "lastPrice": "0.13190000"
    },
    {
      "symbol": "FETUSDT",
      "lastPrice": "0.74200000"
    },
    {
      "symbol": "NEIROUSDT",
      "lastPrice": "0.00043909"
    },
    {
      "symbol": "ACAUSDT",
      "lastPrice": "0.03040000"
    },
    {
      "symbol": "PERPUSDT",
      "lastPrice": "0.30140000"
    },
    {
      "symbol": "POWRUSDT",
      "lastPrice": "0.18200000"
    },
    {
      "symbol": "BICOUSDT",
      "lastPrice": "0.12050000"
    },
    {
      "symbol": "AVAXUSDT",
      "lastPrice": "25.00000000"
    },
    {
      "symbol": "THETAUSDT",
      "lastPrice": "0.90400000"
    },
    {
      "symbol": "PIVXUSDT",
      "lastPrice": "0.15320000"
    },
    {
      "symbol": "MASKUSDT",
      "lastPrice": "1.39100000"
    },
    {
      "symbol": "FLMUSDT",
      "lastPrice": "0.03140000"
    },
    {
      "symbol": "BONKUSDT",
      "lastPrice": "0.00002611"
    },
    {
      "symbol": "ANKRUSDT",
      "lastPrice": "0.01696000"
    },
    {
      "symbol": "JOEUSDT",
      "lastPrice": "0.16960000"
    },
    {
      "symbol": "PNUTUSDT",
      "lastPrice": "0.26000000"
    },
    {
      "symbol": "XAIUSDT",
      "lastPrice": "0.05560000"
    },
    {
      "symbol": "AVAUSDT",
      "lastPrice": "0.62520000"
    },
    {
      "symbol": "IDUSDT",
      "lastPrice": "0.18230000"
    },
    {
      "symbol": "GNOUSDT",
      "lastPrice": "141.62000000"
    },
    {
      "symbol": "PIXELUSDT",
      "lastPrice": "0.03719000"
    },
    {
      "symbol": "ADXUSDT",
      "lastPrice": "0.15080000"
    },
    {
      "symbol": "BABYUSDT",
      "lastPrice": "0.06450000"
    },
    {
      "symbol": "ASTRUSDT",
      "lastPrice": "0.02637000"
    },
    {
      "symbol": "DOTUSDT",
      "lastPrice": "4.21500000"
    },
    {
      "symbol": "INITUSDT",
      "lastPrice": "0.47610000"
    },
    {
      "symbol": "KAVAUSDT",
      "lastPrice": "0.39700000"
    },
    {
      "symbol": "XVSUSDT",
      "lastPrice": "6.73000000"
    },
    {
      "symbol": "CKBUSDT",
      "lastPrice": "0.00577500"
    },
    {
      "symbol": "CHZUSDT",
      "lastPrice": "0.04398000"
    },
    {
      "symbol": "CAKEUSDT",
      "lastPrice": "2.90000000"
    },
    {
      "symbol": "AXLUSDT",
      "lastPrice": "0.36810000"
    },
    {
      "symbol": "REZUSDT",
      "lastPrice": "0.01529000"
    },
    {
      "symbol": "LAYERUSDT",
      "lastPrice": "0.64470000"
    },
    {
      "symbol": "1MBABYDOGEUSDT",
      "lastPrice": "0.00140980"
    },
    {
      "symbol": "PARTIUSDT",
      "lastPrice": "0.20110000"
    },
    {
      "symbol": "APEUSDT",
      "lastPrice": "0.64920000"
    },
    {
      "symbol": "CTKUSDT",
      "lastPrice": "0.37050000"
    },
    {
      "symbol": "BIFIUSDT",
      "lastPrice": "203.00000000"
    },
    {
      "symbol": "STEEMUSDT",
      "lastPrice": "0.13910000"
    },
    {
      "symbol": "RONINUSDT",
      "lastPrice": "0.59100000"
    },
    {
      "symbol": "SOPHUSDT",
      "lastPrice": "0.03985000"
    },
    {
      "symbol": "BNBUSDT",
      "lastPrice": "841.96000000"
    },
    {
      "symbol": "ZENUSDT",
      "lastPrice": "8.62000000"
    },
    {
      "symbol": "ILVUSDT",
      "lastPrice": "18.28000000"
    },
    {
      "symbol": "TRXUSDT",
      "lastPrice": "0.35910000"
    },
    {
      "symbol": "ACEUSDT",
      "lastPrice": "0.60200000"
    },
    {
      "symbol": "TFUELUSDT",
      "lastPrice": "0.03889000"
    },
    {
      "symbol": "TKOUSDT",
      "lastPrice": "0.17850000"
    },
    {
      "symbol": "HIVEUSDT",
      "lastPrice": "0.23050000"
    },
    {
      "symbol": "CELOUSDT",
      "lastPrice": "0.36830000"
    },
    {
      "symbol": "ACHUSDT",
      "lastPrice": "0.02323000"
    },
    {
      "symbol": "RADUSDT",
      "lastPrice": "0.68600000"
    },
    {
      "symbol": "POLUSDT",
      "lastPrice": "0.25050000"
    },
    {
      "symbol": "COOKIEUSDT",
      "lastPrice": "0.15830000"
    },
    {
      "symbol": "SPELLUSDT",
      "lastPrice": "0.00053460"
    },
    {
      "symbol": "AUDIOUSDT",
      "lastPrice": "0.06560000"
    },
    {
      "symbol": "DCRUSDT",
      "lastPrice": "18.06000000"
    },
    {
      "symbol": "HBARUSDT",
      "lastPrice": "0.26258000"
    },
    {
      "symbol": "BTTCUSDT",
      "lastPrice": "0.00000070"
    },
    {
      "symbol": "SHIBUSDT",
      "lastPrice": "0.00001375"
    },
    {
      "symbol": "BERAUSDT",
      "lastPrice": "2.06900000"
    },
    {
      "symbol": "GASUSDT",
      "lastPrice": "3.40400000"
    },
    {
      "symbol": "POLYXUSDT",
      "lastPrice": "0.14880000"
    },
    {
      "symbol": "IOTAUSDT",
      "lastPrice": "0.21470000"
    },
    {
      "symbol": "TUSDT",
      "lastPrice": "0.01788000"
    },
    {
      "symbol": "QUICKUSDT",
      "lastPrice": "0.02488000"
    },
    {
      "symbol": "CETUSUSDT",
      "lastPrice": "0.11370000"
    },
    {
      "symbol": "BANANAUSDT",
      "lastPrice": "26.68000000"
    },
    {
      "symbol": "RLCUSDT",
      "lastPrice": "1.04300000"
    },
    {
      "symbol": "CGPTUSDT",
      "lastPrice": "0.10430000"
    },
    {
      "symbol": "VANAUSDT",
      "lastPrice": "4.57100000"
    },
    {
      "symbol": "SCRUSDT",
      "lastPrice": "0.37600000"
    },
    {
      "symbol": "DFUSDT",
      "lastPrice": "0.03088000"
    },
    {
      "symbol": "XECUSDT",
      "lastPrice": "0.00002220"
    },
    {
      "symbol": "UTKUSDT",
      "lastPrice": "0.03200000"
    },
    {
      "symbol": "BIGTIMEUSDT",
      "lastPrice": "0.06156000"
    },
    {
      "symbol": "SAGAUSDT",
      "lastPrice": "0.28110000"
    },
    {
      "symbol": "LAZIOUSDT",
      "lastPrice": "1.02000000"
    },
    {
      "symbol": "KAITOUSDT",
      "lastPrice": "1.22350000"
    },
    {
      "symbol": "BCHUSDT",
      "lastPrice": "620.10000000"
    },
    {
      "symbol": "IQUSDT",
      "lastPrice": "0.00371100"
    },
    {
      "symbol": "SXTUSDT",
      "lastPrice": "0.08900000"
    },
    {
      "symbol": "ONDOUSDT",
      "lastPrice": "1.06140000"
    },
    {
      "symbol": "FLUXUSDT",
      "lastPrice": "0.23330000"
    },
    {
      "symbol": "VTHOUSDT",
      "lastPrice": "0.00200900"
    },
    {
      "symbol": "OGNUSDT",
      "lastPrice": "0.06570000"
    },
    {
      "symbol": "RVNUSDT",
      "lastPrice": "0.01479000"
    },
    {
      "symbol": "RUNEUSDT",
      "lastPrice": "1.47900000"
    },
    {
      "symbol": "DASHUSDT",
      "lastPrice": "23.77000000"
    },
    {
      "symbol": "ARKUSDT",
      "lastPrice": "0.46420000"
    },
    {
      "symbol": "ETCUSDT",
      "lastPrice": "23.92000000"
    },
    {
      "symbol": "OSMOUSDT",
      "lastPrice": "0.18960000"
    },
    {
      "symbol": "MBLUSDT",
      "lastPrice": "0.00236400"
    },
    {
      "symbol": "GNSUSDT",
      "lastPrice": "2.15800000"
    },
    {
      "symbol": "DATAUSDT",
      "lastPrice": "0.01759000"
    },
    {
      "symbol": "1INCHUSDT",
      "lastPrice": "0.27550000"
    },
    {
      "symbol": "VICUSDT",
      "lastPrice": "0.26880000"
    },
    {
      "symbol": "BANANAS31USDT",
      "lastPrice": "0.00731100"
    },
    {
      "symbol": "PORTOUSDT",
      "lastPrice": "1.03000000"
    },
    {
      "symbol": "PEPEUSDT",
      "lastPrice": "0.00001213"
    },
    {
      "symbol": "NXPCUSDT",
      "lastPrice": "0.93630000"
    },
    {
      "symbol": "ALGOUSDT",
      "lastPrice": "0.27500000"
    },
    {
      "symbol": "AUCTIONUSDT",
      "lastPrice": "10.55000000"
    },
    {
      "symbol": "PYRUSDT",
      "lastPrice": "1.19400000"
    },
    {
      "symbol": "FORTHUSDT",
      "lastPrice": "2.89400000"
    },
    {
      "symbol": "ONGUSDT",
      "lastPrice": "0.18110000"
    },
    {
      "symbol": "METISUSDT",
      "lastPrice": "18.80000000"
    },
    {
      "symbol": "XNOUSDT",
      "lastPrice": "1.03500000"
    },
    {
      "symbol": "MEUSDT",
      "lastPrice": "0.75900000"
    },
    {
      "symbol": "STRAXUSDT",
      "lastPrice": "0.04893000"
    },
    {
      "symbol": "AMPUSDT",
      "lastPrice": "0.00379200"
    },
    {
      "symbol": "SLPUSDT",
      "lastPrice": "0.00202300"
    },
    {
      "symbol": "MOVEUSDT",
      "lastPrice": "0.14480000"
    },
    {
      "symbol": "MBOXUSDT",
      "lastPrice": "0.06290000"
    },
    {
      "symbol": "PONDUSDT",
      "lastPrice": "0.00831000"
    },
    {
      "symbol": "OMUSDT",
      "lastPrice": "0.28060000"
    },
    {
      "symbol": "HOTUSDT",
      "lastPrice": "0.00104400"
    },
    {
      "symbol": "QKCUSDT",
      "lastPrice": "0.00752700"
    },
    {
      "symbol": "COMPUSDT",
      "lastPrice": "53.88000000"
    },
    {
      "symbol": "SCUSDT",
      "lastPrice": "0.00324500"
    },
    {
      "symbol": "BNTUSDT",
      "lastPrice": "0.83770000"
    },
    {
      "symbol": "RAREUSDT",
      "lastPrice": "0.06140000"
    },
    {
      "symbol": "DEGOUSDT",
      "lastPrice": "1.25900000"
    },
    {
      "symbol": "1000CATUSDT",
      "lastPrice": "0.00948000"
    },
    {
      "symbol": "DOGSUSDT",
      "lastPrice": "0.00014870"
    },
    {
      "symbol": "ACTUSDT",
      "lastPrice": "0.04420000"
    },
    {
      "symbol": "LSKUSDT",
      "lastPrice": "0.44300000"
    },
    {
      "symbol": "CATIUSDT",
      "lastPrice": "0.09700000"
    },
    {
      "symbol": "TURBOUSDT",
      "lastPrice": "0.00491600"
    },
    {
      "symbol": "FISUSDT",
      "lastPrice": "0.12310000"
    },
    {
      "symbol": "JSTUSDT",
      "lastPrice": "0.03434000"
    },
    {
      "symbol": "TSTUSDT",
      "lastPrice": "0.02678000"
    },
    {
      "symbol": "KNCUSDT",
      "lastPrice": "0.43480000"
    },
    {
      "symbol": "LUNAUSDT",
      "lastPrice": "0.16770000"
    },
    {
      "symbol": "QNTUSDT",
      "lastPrice": "115.86000000"
    },
    {
      "symbol": "IDEXUSDT",
      "lastPrice": "0.02667000"
    },
    {
      "symbol": "XRPUSDT",
      "lastPrice": "3.26030000"
    },
    {
      "symbol": "FARMUSDT",
      "lastPrice": "31.06000000"
    },
    {
      "symbol": "QIUSDT",
      "lastPrice": "0.00758000"
    },
    {
      "symbol": "SYNUSDT",
      "lastPrice": "0.14740000"
    },
    {
      "symbol": "WBTCUSDT",
      "lastPrice": "121165.02000000"
    },
    {
      "symbol": "BTCUSDT",
      "lastPrice": "121219.19000000"
    },
    {
      "symbol": "XVGUSDT",
      "lastPrice": "0.00724700"
    },
    {
      "symbol": "BEAMXUSDT",
      "lastPrice": "0.00846000"
    },
    {
      "symbol": "BROCCOLI714USDT",
      "lastPrice": "0.02859000"
    },
    {
      "symbol": "ACMUSDT",
      "lastPrice": "1.12300000"
    },
    {
      "symbol": "AIXBTUSDT",
      "lastPrice": "0.13420000"
    },
    {
      "symbol": "ARDRUSDT",
      "lastPrice": "0.09526000"
    },
    {
      "symbol": "HAEDALUSDT",
      "lastPrice": "0.14520000"
    },
    {
      "symbol": "NEXOUSDT",
      "lastPrice": "1.36700000"
    },
    {
      "symbol": "ENSUSDT",
      "lastPrice": "29.28000000"
    },
    {
      "symbol": "TONUSDT",
      "lastPrice": "3.46000000"
    },
    {
      "symbol": "MOVRUSDT",
      "lastPrice": "6.82800000"
    },
    {
      "symbol": "PORTALUSDT",
      "lastPrice": "0.05130000"
    },
    {
      "symbol": "XLMUSDT",
      "lastPrice": "0.44850000"
    },
    {
      "symbol": "FORMUSDT",
      "lastPrice": "3.82190000"
    },
    {
      "symbol": "SSVUSDT",
      "lastPrice": "10.63000000"
    },
    {
      "symbol": "RPLUSDT",
      "lastPrice": "8.80000000"
    },
    {
      "symbol": "ALTUSDT",
      "lastPrice": "0.03826000"
    },
    {
      "symbol": "LQTYUSDT",
      "lastPrice": "1.04800000"
    },
    {
      "symbol": "ZECUSDT",
      "lastPrice": "39.33000000"
    },
    {
      "symbol": "FXSUSDT",
      "lastPrice": "3.16800000"
    },
    {
      "symbol": "BARUSDT",
      "lastPrice": "1.30800000"
    },
    {
      "symbol": "SAHARAUSDT",
      "lastPrice": "0.09560000"
    },
    {
      "symbol": "OMNIUSDT",
      "lastPrice": "4.36000000"
    },
    {
      "symbol": "A2ZUSDT",
      "lastPrice": "0.00740200"
    },
    {
      "symbol": "VOXELUSDT",
      "lastPrice": "0.06080000"
    },
    {
      "symbol": "NEWTUSDT",
      "lastPrice": "0.34900000"
    },
    {
      "symbol": "EURUSDT",
      "lastPrice": "1.17200000"
    },
    {
      "symbol": "LISTAUSDT",
      "lastPrice": "0.30730000"
    },
    {
      "symbol": "SLFUSDT",
      "lastPrice": "0.06830000"
    },
    {
      "symbol": "SFPUSDT",
      "lastPrice": "0.51510000"
    },
    {
      "symbol": "COWUSDT",
      "lastPrice": "0.42450000"
    },
    {
      "symbol": "MDTUSDT",
      "lastPrice": "0.02537000"
    },
    {
      "symbol": "STGUSDT",
      "lastPrice": "0.18950000"
    },
    {
      "symbol": "EURIUSDT",
      "lastPrice": "1.17160000"
    },
    {
      "symbol": "GPSUSDT",
      "lastPrice": "0.01601000"
    },
    {
      "symbol": "BMTUSDT",
      "lastPrice": "0.08400000"
    },
    {
      "symbol": "1000CHEEMSUSDT",
      "lastPrice": "0.00130900"
    },
    {
      "symbol": "LUNCUSDT",
      "lastPrice": "0.00006236"
    },
    {
      "symbol": "VIRTUALUSDT",
      "lastPrice": "1.35850000"
    },
    {
      "symbol": "JUVUSDT",
      "lastPrice": "1.35300000"
    },
    {
      "symbol": "BCCUSDT",
      "lastPrice": "0.00000000"
    },
    {
      "symbol": "EOSUSDT",
      "lastPrice": "0.00000000"
    },
    {
      "symbol": "VENUSDT",
      "lastPrice": "0.00000000"
    },
    {
      "symbol": "NULSUSDT",
      "lastPrice": "0.00000000"
    },
    {
      "symbol": "PAXUSDT",
      "lastPrice": "0.00000000"
    },
    {
      "symbol": "BCHABCUSDT",
      "lastPrice": "0.00000000"
    },
    {
      "symbol": "BCHSVUSDT",
      "lastPrice": "0.00000000"
    },
    {
      "symbol": "WAVESUSDT",
      "lastPrice": "0.00000000"
    },
    {
      "symbol": "BTTUSDT",
      "lastPrice": "0.00000000"
    },
    {
      "symbol": "USDSUSDT",
      "lastPrice": "0.00000000"
    },
    {
      "symbol": "XMRUSDT",
      "lastPrice": "0.00000000"
    },
    {
      "symbol": "NANOUSDT",
      "lastPrice": "0.00000000"
    },
    {
      "symbol": "OMGUSDT",
      "lastPrice": "0.00000000"
    },
    {
      "symbol": "MITHUSDT",
      "lastPrice": "0.00000000"
    },
    {
      "symbol": "MATICUSDT",
      "lastPrice": "0.00000000"
    },
    {
      "symbol": "FTMUSDT",
      "lastPrice": "0.00000000"
    },
    {
      "symbol": "USDSBUSDT",
      "lastPrice": "0.00000000"
    },
    {
      "symbol": "GTOUSDT",
      "lastPrice": "0.00000000"
    },
    {
      "symbol": "ERDUSDT",
      "lastPrice": "0.00000000"
    },
    {
      "symbol": "NPXSUSDT",
      "lastPrice": "0.00000000"
    },
    {
      "symbol": "COCOSUSDT",
      "lastPrice": "0.00000000"
    },
    {
      "symbol": "TOMOUSDT",
      "lastPrice": "0.00000000"
    },
    {
      "symbol": "PERLUSDT",
      "lastPrice": "0.00000000"
    },
    {
      "symbol": "MFTUSDT",
      "lastPrice": "0.00000000"
    },
    {
      "symbol": "KEYUSDT",
      "lastPrice": "0.00000000"
    },
    {
      "symbol": "STORMUSDT",
      "lastPrice": "0.00000000"
    },
    {
      "symbol": "DOCKUSDT",
      "lastPrice": "0.00000000"
    },
    {
      "symbol": "BUSDUSDT",
      "lastPrice": "0.00000000"
    },
    {
      "symbol": "BEAMUSDT",
      "lastPrice": "0.00000000"
    },
    {
      "symbol": "RENUSDT",
      "lastPrice": "0.00000000"
    },
    {
      "symbol": "HCUSDT",
      "lastPrice": "0.00000000"
    },
    {
      "symbol": "MCOUSDT",
      "lastPrice": "0.00000000"
    },
    {
      "symbol": "CTXCUSDT",
      "lastPrice": "0.00000000"
    },
    {
      "symbol": "TROYUSDT",
      "lastPrice": "0.00000000"
    },
    {
      "symbol": "VITEUSDT",
      "lastPrice": "0.00000000"
    },
    {
      "symbol": "DREPUSDT",
      "lastPrice": "0.00000000"
    },
    {
      "symbol": "BULLUSDT",
      "lastPrice": "0.00000000"
    },
    {
      "symbol": "BEARUSDT",
      "lastPrice": "0.00000000"
    },
    {
      "symbol": "ETHBULLUSDT",
      "lastPrice": "0.00000000"
    },
    {
      "symbol": "ETHBEARUSDT",
      "lastPrice": "0.00000000"
    },
    {
      "symbol": "TCTUSDT",
      "lastPrice": "0.00000000"
    },
    {
      "symbol": "WRXUSDT",
      "lastPrice": "0.00000000"
    },
    {
      "symbol": "BTSUSDT",
      "lastPrice": "0.00000000"
    },
    {
      "symbol": "EOSBULLUSDT",
      "lastPrice": "0.00000000"
    },
    {
      "symbol": "EOSBEARUSDT",
      "lastPrice": "0.00000000"
    },
    {
      "symbol": "XRPBULLUSDT",
      "lastPrice": "0.00000000"
    },
    {
      "symbol": "XRPBEARUSDT",
      "lastPrice": "0.00000000"
    },
    {
      "symbol": "STRATUSDT",
      "lastPrice": "0.00000000"
    },
    {
      "symbol": "AIONUSDT",
      "lastPrice": "0.00000000"
    },
    {
      "symbol": "BNBBULLUSDT",
      "lastPrice": "0.00000000"
    },
    {
      "symbol": "BNBBEARUSDT",
      "lastPrice": "0.00000000"
    },
    {
      "symbol": "STPTUSDT",
      "lastPrice": "0.00000000"
    },
    {
      "symbol": "WTCUSDT",
      "lastPrice": "0.00000000"
    },
    {
      "symbol": "XZCUSDT",
      "lastPrice": "0.00000000"
    },
    {
      "symbol": "BTCUPUSDT",
      "lastPrice": "0.00000000"
    },
    {
      "symbol": "BTCDOWNUSDT",
      "lastPrice": "0.00000000"
    },
    {
      "symbol": "GXSUSDT",
      "lastPrice": "0.00000000"
    },
    {
      "symbol": "LENDUSDT",
      "lastPrice": "0.00000000"
    },
    {
      "symbol": "STMXUSDT",
      "lastPrice": "0.00000000"
    },
    {
      "symbol": "REPUSDT",
      "lastPrice": "0.00000000"
    },
    {
      "symbol": "PNTUSDT",
      "lastPrice": "0.00000000"
    },
    {
      "symbol": "BKRWUSDT",
      "lastPrice": "0.00000000"
    },
    {
      "symbol": "ETHUPUSDT",
      "lastPrice": "0.00000000"
    },
    {
      "symbol": "ETHDOWNUSDT",
      "lastPrice": "0.00000000"
    },
    {
      "symbol": "ADAUPUSDT",
      "lastPrice": "0.00000000"
    },
    {
      "symbol": "ADADOWNUSDT",
      "lastPrice": "0.00000000"
    },
    {
      "symbol": "LINKUPUSDT",
      "lastPrice": "0.00000000"
    },
    {
      "symbol": "LINKDOWNUSDT",
      "lastPrice": "0.00000000"
    },
    {
      "symbol": "GBPUSDT",
      "lastPrice": "0.00000000"
    },
    {
      "symbol": "DAIUSDT",
      "lastPrice": "0.00000000"
    },
    {
      "symbol": "BNBUPUSDT",
      "lastPrice": "0.00000000"
    },
    {
      "symbol": "BNBDOWNUSDT",
      "lastPrice": "0.00000000"
    },
    {
      "symbol": "XTZUPUSDT",
      "lastPrice": "0.00000000"
    },
    {
      "symbol": "XTZDOWNUSDT",
      "lastPrice": "0.00000000"
    },
    {
      "symbol": "AUDUSDT",
      "lastPrice": "0.00000000"
    },
    {
      "symbol": "BALUSDT",
      "lastPrice": "0.00000000"
    },
    {
      "symbol": "BLZUSDT",
      "lastPrice": "0.00000000"
    },
    {
      "symbol": "IRISUSDT",
      "lastPrice": "0.00000000"
    },
    {
      "symbol": "SRMUSDT",
      "lastPrice": "0.00000000"
    },
    {
      "symbol": "ANTUSDT",
      "lastPrice": "0.00000000"
    },
    {
      "symbol": "OCEANUSDT",
      "lastPrice": "0.00000000"
    },
    {
      "symbol": "WNXMUSDT",
      "lastPrice": "0.00000000"
    },
    {
      "symbol": "BZRXUSDT",
      "lastPrice": "0.00000000"
    },
    {
      "symbol": "YFIIUSDT",
      "lastPrice": "0.00000000"
    },
    {
      "symbol": "EOSUPUSDT",
      "lastPrice": "0.00000000"
    },
    {
      "symbol": "EOSDOWNUSDT",
      "lastPrice": "0.00000000"
    },
    {
      "symbol": "TRXUPUSDT",
      "lastPrice": "0.00000000"
    },
    {
      "symbol": "TRXDOWNUSDT",
      "lastPrice": "0.00000000"
    },
    {
      "symbol": "XRPUPUSDT",
      "lastPrice": "0.00000000"
    },
    {
      "symbol": "XRPDOWNUSDT",
      "lastPrice": "0.00000000"
    },
    {
      "symbol": "DOTUPUSDT",
      "lastPrice": "0.00000000"
    },
    {
      "symbol": "DOTDOWNUSDT",
      "lastPrice": "0.00000000"
    },
    {
      "symbol": "WINGUSDT",
      "lastPrice": "0.00000000"
    },
    {
      "symbol": "LTCUPUSDT",
      "lastPrice": "0.00000000"
    },
    {
      "symbol": "LTCDOWNUSDT",
      "lastPrice": "0.00000000"
    },
    {
      "symbol": "NBSUSDT",
      "lastPrice": "0.00000000"
    },
    {
      "symbol": "HNTUSDT",
      "lastPrice": "0.00000000"
    },
    {
      "symbol": "UNIUPUSDT",
      "lastPrice": "0.00000000"
    },
    {
      "symbol": "UNIDOWNUSDT",
      "lastPrice": "0.00000000"
    },
    {
      "symbol": "ORNUSDT",
      "lastPrice": "0.00000000"
    },
    {
      "symbol": "SXPUPUSDT",
      "lastPrice": "0.00000000"
    },
    {
      "symbol": "SXPDOWNUSDT",
      "lastPrice": "0.00000000"
    },
    {
      "symbol": "FILUPUSDT",
      "lastPrice": "0.00000000"
    },
    {
      "symbol": "FILDOWNUSDT",
      "lastPrice": "0.00000000"
    },
    {
      "symbol": "YFIUPUSDT",
      "lastPrice": "0.00000000"
    },
    {
      "symbol": "YFIDOWNUSDT",
      "lastPrice": "0.00000000"
    },
    {
      "symbol": "BCHUPUSDT",
      "lastPrice": "0.00000000"
    },
    {
      "symbol": "BCHDOWNUSDT",
      "lastPrice": "0.00000000"
    },
    {
      "symbol": "AKROUSDT",
      "lastPrice": "0.00000000"
    },
    {
      "symbol": "HARDUSDT",
      "lastPrice": "0.00000000"
    },
    {
      "symbol": "DNTUSDT",
      "lastPrice": "0.00000000"
    },
    {
      "symbol": "UNFIUSDT",
      "lastPrice": "0.00000000"
    },
    {
      "symbol": "XEMUSDT",
      "lastPrice": "0.00000000"
    },
    {
      "symbol": "AAVEUPUSDT",
      "lastPrice": "0.00000000"
    },
    {
      "symbol": "AAVEDOWNUSDT",
      "lastPrice": "0.00000000"
    },
    {
      "symbol": "SUSDUSDT",
      "lastPrice": "0.00000000"
    },
    {
      "symbol": "SUSHIUPUSDT",
      "lastPrice": "0.00000000"
    },
    {
      "symbol": "SUSHIDOWNUSDT",
      "lastPrice": "0.00000000"
    },
    {
      "symbol": "XLMUPUSDT",
      "lastPrice": "0.00000000"
    },
    {
      "symbol": "XLMDOWNUSDT",
      "lastPrice": "0.00000000"
    },
    {
      "symbol": "REEFUSDT",
      "lastPrice": "0.00000000"
    },
    {
      "symbol": "BTCSTUSDT",
      "lastPrice": "0.00000000"
    },
    {
      "symbol": "FIROUSDT",
      "lastPrice": "0.00000000"
    },
    {
      "symbol": "LITUSDT",
      "lastPrice": "0.00000000"
    },
    {
      "symbol": "BADGERUSDT",
      "lastPrice": "0.00000000"
    },
    {
      "symbol": "LINAUSDT",
      "lastPrice": "0.00000000"
    },
    {
      "symbol": "RAMPUSDT",
      "lastPrice": "0.00000000"
    },
    {
      "symbol": "EPSUSDT",
      "lastPrice": "0.00000000"
    },
    {
      "symbol": "AUTOUSDT",
      "lastPrice": "0.00000000"
    },
    {
      "symbol": "1INCHUPUSDT",
      "lastPrice": "0.00000000"
    },
    {
      "symbol": "1INCHDOWNUSDT",
      "lastPrice": "0.00000000"
    },
    {
      "symbol": "BTGUSDT",
      "lastPrice": "0.00000000"
    },
    {
      "symbol": "MIRUSDT",
      "lastPrice": "0.00000000"
    },
    {
      "symbol": "BURGERUSDT",
      "lastPrice": "0.00000000"
    },
    {
      "symbol": "POLSUSDT",
      "lastPrice": "0.00000000"
    },
    {
      "symbol": "MDXUSDT",
      "lastPrice": "0.00000000"
    },
    {
      "symbol": "NUUSDT",
      "lastPrice": "0.00000000"
    },
    {
      "symbol": "TORNUSDT",
      "lastPrice": "0.00000000"
    },
    {
      "symbol": "KEEPUSDT",
      "lastPrice": "0.00000000"
    },
    {
      "symbol": "ERNUSDT",
      "lastPrice": "0.00000000"
    },
    {
      "symbol": "KLAYUSDT",
      "lastPrice": "0.00000000"
    },
    {
      "symbol": "BONDUSDT",
      "lastPrice": "0.00000000"
    },
    {
      "symbol": "CLVUSDT",
      "lastPrice": "0.00000000"
    },
    {
      "symbol": "TVKUSDT",
      "lastPrice": "0.00000000"
    },
    {
      "symbol": "ALPACAUSDT",
      "lastPrice": "0.00000000"
    },
    {
      "symbol": "FORUSDT",
      "lastPrice": "0.00000000"
    },
    {
      "symbol": "TRIBEUSDT",
      "lastPrice": "0.00000000"
    },
    {
      "symbol": "ELFUSDT",
      "lastPrice": "0.00000000"
    },
    {
      "symbol": "POLYUSDT",
      "lastPrice": "0.00000000"
    },
    {
      "symbol": "VIDTUSDT",
      "lastPrice": "0.00000000"
    },
    {
      "symbol": "FRONTUSDT",
      "lastPrice": "0.00000000"
    },
    {
      "symbol": "CVPUSDT",
      "lastPrice": "0.00000000"
    },
    {
      "symbol": "BETAUSDT",
      "lastPrice": "0.00000000"
    },
    {
      "symbol": "DARUSDT",
      "lastPrice": "0.00000000"
    },
    {
      "symbol": "BNXUSDT",
      "lastPrice": "0.00000000"
    },
    {
      "symbol": "RGTUSDT",
      "lastPrice": "0.00000000"
    },
    {
      "symbol": "KP3RUSDT",
      "lastPrice": "0.00000000"
    },
    {
      "symbol": "VGXUSDT",
      "lastPrice": "0.00000000"
    },
    {
      "symbol": "PLAUSDT",
      "lastPrice": "0.00000000"
    },
    {
      "symbol": "RNDRUSDT",
      "lastPrice": "0.00000000"
    },
    {
      "symbol": "MCUSDT",
      "lastPrice": "0.00000000"
    },
    {
      "symbol": "ANYUSDT",
      "lastPrice": "0.00000000"
    },
    {
      "symbol": "OOKIUSDT",
      "lastPrice": "0.00000000"
    },
    {
      "symbol": "USTUSDT",
      "lastPrice": "0.00000000"
    },
    {
      "symbol": "ANCUSDT",
      "lastPrice": "0.00000000"
    },
    {
      "symbol": "NBTUSDT",
      "lastPrice": "0.00000000"
    },
    {
      "symbol": "MULTIUSDT",
      "lastPrice": "0.00000000"
    },
    {
      "symbol": "MOBUSDT",
      "lastPrice": "0.00000000"
    },
    {
      "symbol": "GALUSDT",
      "lastPrice": "0.00000000"
    },
    {
      "symbol": "EPXUSDT",
      "lastPrice": "0.00000000"
    },
    {
      "symbol": "NEBLUSDT",
      "lastPrice": "0.00000000"
    },
    {
      "symbol": "MAGICUSDT",
      "lastPrice": "0.27050000"
    },
    {
      "symbol": "PROSUSDT",
      "lastPrice": "0.00000000"
    },
    {
      "symbol": "AGIXUSDT",
      "lastPrice": "0.00000000"
    },
    {
      "symbol": "VIBUSDT",
      "lastPrice": "0.00000000"
    },
    {
      "symbol": "AMBUSDT",
      "lastPrice": "0.00000000"
    },
    {
      "symbol": "BETHUSDT",
      "lastPrice": "0.00000000"
    },
    {
      "symbol": "UFTUSDT",
      "lastPrice": "0.00000000"
    },
    {
      "symbol": "LOOMUSDT",
      "lastPrice": "0.00000000"
    },
    {
      "symbol": "OAXUSDT",
      "lastPrice": "0.00000000"
    },
    {
      "symbol": "AERGOUSDT",
      "lastPrice": "0.00000000"
    },
    {
      "symbol": "ASTUSDT",
      "lastPrice": "0.00000000"
    },
    {
      "symbol": "SNTUSDT",
      "lastPrice": "0.00000000"
    },
    {
      "symbol": "COMBOUSDT",
      "lastPrice": "0.00000000"
    },
    {
      "symbol": "CREAMUSDT",
      "lastPrice": "0.00000000"
    },
    {
      "symbol": "GFTUSDT",
      "lastPrice": "0.00000000"
    },
    {
      "symbol": "PDAUSDT",
      "lastPrice": "0.00000000"
    },
    {
      "symbol": "XUSDUSDT",
      "lastPrice": "1.00010000"
    },
    {
      "symbol": "USD1USDT",
      "lastPrice": "0.99990000"
    },
    {
      "symbol": "USDCUSDT",
      "lastPrice": "0.99970000"
    },
    {
      "symbol": "PAXGUSDT",
      "lastPrice": "3348.33000000"
    },
    {
      "symbol": "CUSDT",
      "lastPrice": "0.26260000"
    },
    {
      "symbol": "USDPUSDT",
      "lastPrice": "0.99960000"
    },
    {
      "symbol": "FDUSDUSDT",
      "lastPrice": "0.99770000"
    },
    {
      "symbol": "TUSDUSDT",
      "lastPrice": "0.99740000"
    },
    {
      "symbol": "BFUSDUSDT",
      "lastPrice": "0.99940000"
    },
    {
      "symbol": "CITYUSDT",
      "lastPrice": "1.12500000"
    },
    {
      "symbol": "AWEUSDT",
      "lastPrice": "0.05410000"
    },
    {
      "symbol": "GUNUSDT",
      "lastPrice": "0.03085000"
    },
    {
      "symbol": "CHESSUSDT",
      "lastPrice": "0.07520000"
    },
    {
      "symbol": "RSRUSDT",
      "lastPrice": "0.00958400"
    },
    {
      "symbol": "HYPERUSDT",
      "lastPrice": "0.38400000"
    },
    {
      "symbol": "TREEUSDT",
      "lastPrice": "0.42210000"
    },
    {
      "symbol": "SOLVUSDT",
      "lastPrice": "0.04236000"
    },
    {
      "symbol": "PROVEUSDT",
      "lastPrice": "1.46200000"
    },
    {
      "symbol": "EPICUSDT",
      "lastPrice": "2.10500000"
    },
    {
      "symbol": "EDUUSDT",
      "lastPrice": "0.14870000"
    },
    {
      "symbol": "DEXEUSDT",
      "lastPrice": "7.54800000"
    },
    {
      "symbol": "FIOUSDT",
      "lastPrice": "0.02088000"
    },
    {
      "symbol": "GHSTUSDT",
      "lastPrice": "0.50700000"
    },
    {
      "symbol": "GMXUSDT",
      "lastPrice": "17.03000000"
    },
    {
      "symbol": "PENGUUSDT",
      "lastPrice": "0.03665200"
    },
    {
      "symbol": "SANTOSUSDT",
      "lastPrice": "2.78700000"
    },
    {
      "symbol": "PENDLEUSDT",
      "lastPrice": "5.59300000"
    },
    {
      "symbol": "MUBARAKUSDT",
      "lastPrice": "0.03753000"
    },
    {
      "symbol": "FUNUSDT",
      "lastPrice": "0.00931600"
    },
    {
      "symbol": "PSGUSDT",
      "lastPrice": "1.94500000"
    },
    {
      "symbol": "LINKUSDT",
      "lastPrice": "23.45000000"
    },
    {
      "symbol": "CFXUSDT",
      "lastPrice": "0.19640000"
    },
    {
      "symbol": "HUMAUSDT",
      "lastPrice": "0.03686000"
    },
    {
      "symbol": "HFTUSDT",
      "lastPrice": "0.09620000"
    },
    {
      "symbol": "MKRUSDT",
      "lastPrice": "1977.00000000"
    },
    {
      "symbol": "REQUSDT",
      "lastPrice": "0.15220000"
    },
    {
      "symbol": "DIAUSDT",
      "lastPrice": "0.84120000"
    },
    {
      "symbol": "REDUSDT",
      "lastPrice": "0.41730000"
    },
    {
      "symbol": "HIFIUSDT",
      "lastPrice": "0.09440000"
    },
    {
      "symbol": "XTZUSDT",
      "lastPrice": "0.87680000"
    },
    {
      "symbol": "ZROUSDT",
      "lastPrice": "2.30100000"
    },
    {
      "symbol": "ATMUSDT",
      "lastPrice": "1.56100000"
    },
    {
      "symbol": "USTCUSDT",
      "lastPrice": "0.01437000"
    },
    {
      "symbol": "ERAUSDT",
      "lastPrice": "1.00390000"
    },
    {
      "symbol": "TUTUSDT",
      "lastPrice": "0.05943000"
    },
    {
      "symbol": "STOUSDT",
      "lastPrice": "0.09950000"
    },
    {
      "symbol": "HEIUSDT",
      "lastPrice": "0.49660000"
    },
    {
      "symbol": "SYRUPUSDT",
      "lastPrice": "0.45980000"
    },
    {
      "symbol": "AEURUSDT",
      "lastPrice": "1.09070000"
    },
    {
      "symbol": "ENAUSDT",
      "lastPrice": "0.77370000"
    },
    {
      "symbol": "LDOUSDT",
      "lastPrice": "1.49300000"
    },
    {
      "symbol": "NOTUSDT",
      "lastPrice": "0.00209600"
    },
    {
      "symbol": "BIOUSDT",
      "lastPrice": "0.11760000"
    },
    {
      "symbol": "PROMUSDT",
      "lastPrice": "9.58600000"
    },
    {
      "symbol": "CYBERUSDT",
      "lastPrice": "2.85400000"
    },
    {
      "symbol": "ASRUSDT",
      "lastPrice": "6.00500000"
    },
    {
      "symbol": "LAUSDT",
      "lastPrice": "0.37950000"
    },
    {
      "symbol": "SPKUSDT",
      "lastPrice": "0.09389200"
    },
    {
      "symbol": "SHELLUSDT",
      "lastPrice": "0.15720000"
    },
    {
      "symbol": "UMAUSDT",
      "lastPrice": "1.36600000"
    },
    {
      "symbol": "ALPHAUSDT",
      "lastPrice": "0.00970000"
    },
    {
      "symbol": "BSWUSDT",
      "lastPrice": "0.01120000"
    },
    {
      "symbol": "LEVERUSDT",
      "lastPrice": "0.00017500"
    },
    {
      "symbol": "KMDUSDT",
      "lastPrice": "0.01630000"
    },
    {
      "symbol": "LTOUSDT",
      "lastPrice": "0.00380000"
    }
  ]
}